{
  "competicion": {
    "nombre": "Tercera Federación - Grupo X (Grupo 10)",
    "temporada": "2025-26",
    "ultima_actualizacion": "2026-03-11"
  },
  "equipos": [
    {
      "id": 1,
      "nombre": "AD Ceuta B"
    },
    {
      "id": 2,
      "nombre": "Atl. Onubense"
    },
    {
      "id": 3,
      "nombre": "Atletico Central"
    },
    {
      "id": 4,
      "nombre": "Bollullos"
    },
    {
      "id": 5,
      "nombre": "Castilleja"
    },
    {
      "id": 6,
      "nombre": "Chiclana"
    },
    {
      "id": 7,
      "nombre": "Ciudad de Lucena"
    },
    {
      "id": 8,
      "nombre": "Conil"
    },
    {
      "id": 9,
      "nombre": "Coria C.F."
    },
    {
      "id": 10,
      "nombre": "Cádiz B"
    },
    {
      "id": 11,
      "nombre": "Córdoba B"
    },
    {
      "id": 12,
      "nombre": "Dos Hermanas"
    },
    {
      "id": 13,
      "nombre": "Pozoblanco"
    },
    {
      "id": 14,
      "nombre": "RB Linense"
    },
    {
      "id": 15,
      "nombre": "San Roque de Lepe"
    },
    {
      "id": 16,
      "nombre": "Sevilla C"
    },
    {
      "id": 17,
      "nombre": "Tomares"
    },
    {
      "id": 18,
      "nombre": "Utrera"
    }
  ],
  "partidos": [
    {
      "fixture_id": "dloSdeE5",
      "jornada": 1,
      "fecha": "2025-09-05",
      "local": 13,
      "local_nombre": "Pozoblanco",
      "visitante": 1,
      "visitante_nombre": "AD Ceuta B",
      "goles_local": 3,
      "goles_visitante": 0,
      "estado": "jugado"
    },
    {
      "fixture_id": "hdlB0wFt",
      "jornada": 1,
      "fecha": "2025-09-07",
      "local": 14,
      "local_nombre": "RB Linense",
      "visitante": 6,
      "visitante_nombre": "Chiclana",
      "goles_local": 1,
      "goles_visitante": 2,
      "estado": "jugado"
    },
    {
      "fixture_id": "8Uqierw1",
      "jornada": 1,
      "fecha": "2025-09-07",
      "local": 4,
      "local_nombre": "Bollullos",
      "visitante": 3,
      "visitante_nombre": "Atletico Central",
      "goles_local": 3,
      "goles_visitante": 0,
      "estado": "jugado"
    },
    {
      "fixture_id": "04tqc48l",
      "jornada": 1,
      "fecha": "2025-09-07",
      "local": 7,
      "local_nombre": "Ciudad de Lucena",
      "visitante": 18,
      "visitante_nombre": "Utrera",
      "goles_local": 3,
      "goles_visitante": 2,
      "estado": "jugado"
    },
    {
      "fixture_id": "I3ZzeZrI",
      "jornada": 1,
      "fecha": "2025-09-07",
      "local": 15,
      "local_nombre": "San Roque de Lepe",
      "visitante": 9,
      "visitante_nombre": "Coria C.F.",
      "goles_local": 2,
      "goles_visitante": 0,
      "estado": "jugado"
    },
    {
      "fixture_id": "jVnrgDDU",
      "jornada": 1,
      "fecha": "2025-09-07",
      "local": 17,
      "local_nombre": "Tomares",
      "visitante": 5,
      "visitante_nombre": "Castilleja",
      "goles_local": 0,
      "goles_visitante": 0,
      "estado": "jugado"
    },
    {
      "fixture_id": "lOsKbHqg",
      "jornada": 1,
      "fecha": "2025-09-07",
      "local": 2,
      "local_nombre": "Atl. Onubense",
      "visitante": 11,
      "visitante_nombre": "Córdoba B",
      "goles_local": 1,
      "goles_visitante": 1,
      "estado": "jugado"
    },
    {
      "fixture_id": "GW4C2QpR",
      "jornada": 1,
      "fecha": "2025-09-07",
      "local": 10,
      "local_nombre": "Cádiz B",
      "visitante": 12,
      "visitante_nombre": "Dos Hermanas",
      "goles_local": 3,
      "goles_visitante": 1,
      "estado": "jugado"
    },
    {
      "fixture_id": "2Tx0gM7D",
      "jornada": 1,
      "fecha": "2025-09-07",
      "local": 16,
      "local_nombre": "Sevilla C",
      "visitante": 8,
      "visitante_nombre": "Conil",
      "goles_local": 1,
      "goles_visitante": 0,
      "estado": "jugado"
    },
    {
      "fixture_id": "CvzqOXC4",
      "jornada": 2,
      "fecha": "2025-09-13",
      "local": 1,
      "local_nombre": "AD Ceuta B",
      "visitante": 2,
      "visitante_nombre": "Atl. Onubense",
      "goles_local": 1,
      "goles_visitante": 1,
      "estado": "jugado"
    },
    {
      "fixture_id": "4flhKkCT",
      "jornada": 2,
      "fecha": "2025-09-14",
      "local": 5,
      "local_nombre": "Castilleja",
      "visitante": 15,
      "visitante_nombre": "San Roque de Lepe",
      "goles_local": 0,
      "goles_visitante": 0,
      "estado": "jugado"
    },
    {
      "fixture_id": "byA99YcB",
      "jornada": 2,
      "fecha": "2025-09-14",
      "local": 3,
      "local_nombre": "Atletico Central",
      "visitante": 7,
      "visitante_nombre": "Ciudad de Lucena",
      "goles_local": 1,
      "goles_visitante": 0,
      "estado": "jugado"
    },
    {
      "fixture_id": "l6ll2jjo",
      "jornada": 2,
      "fecha": "2025-09-14",
      "local": 6,
      "local_nombre": "Chiclana",
      "visitante": 16,
      "visitante_nombre": "Sevilla C",
      "goles_local": 0,
      "goles_visitante": 2,
      "estado": "jugado"
    },
    {
      "fixture_id": "4YCH7CSN",
      "jornada": 2,
      "fecha": "2025-09-14",
      "local": 8,
      "local_nombre": "Conil",
      "visitante": 4,
      "visitante_nombre": "Bollullos",
      "goles_local": 1,
      "goles_visitante": 1,
      "estado": "jugado"
    },
    {
      "fixture_id": "GCtzQgrh",
      "jornada": 2,
      "fecha": "2025-09-14",
      "local": 11,
      "local_nombre": "Córdoba B",
      "visitante": 14,
      "visitante_nombre": "RB Linense",
      "goles_local": 2,
      "goles_visitante": 0,
      "estado": "jugado"
    },
    {
      "fixture_id": "phYjMBsH",
      "jornada": 2,
      "fecha": "2025-09-14",
      "local": 9,
      "local_nombre": "Coria C.F.",
      "visitante": 13,
      "visitante_nombre": "Pozoblanco",
      "goles_local": 1,
      "goles_visitante": 2,
      "estado": "jugado"
    },
    {
      "fixture_id": "UeIhDGbn",
      "jornada": 2,
      "fecha": "2025-09-14",
      "local": 12,
      "local_nombre": "Dos Hermanas",
      "visitante": 17,
      "visitante_nombre": "Tomares",
      "goles_local": 3,
      "goles_visitante": 0,
      "estado": "jugado"
    },
    {
      "fixture_id": "29G0BfTb",
      "jornada": 2,
      "fecha": "2025-09-14",
      "local": 18,
      "local_nombre": "Utrera",
      "visitante": 10,
      "visitante_nombre": "Cádiz B",
      "goles_local": 0,
      "goles_visitante": 1,
      "estado": "jugado"
    },
    {
      "fixture_id": "6yGOIchM",
      "jornada": 3,
      "fecha": "2025-09-21",
      "local": 4,
      "local_nombre": "Bollullos",
      "visitante": 6,
      "visitante_nombre": "Chiclana",
      "goles_local": 2,
      "goles_visitante": 1,
      "estado": "jugado"
    },
    {
      "fixture_id": "bZf3BFpd",
      "jornada": 3,
      "fecha": "2025-09-21",
      "local": 14,
      "local_nombre": "RB Linense",
      "visitante": 1,
      "visitante_nombre": "AD Ceuta B",
      "goles_local": 2,
      "goles_visitante": 2,
      "estado": "jugado"
    },
    {
      "fixture_id": "QumkZIx3",
      "jornada": 3,
      "fecha": "2025-09-21",
      "local": 2,
      "local_nombre": "Atl. Onubense",
      "visitante": 9,
      "visitante_nombre": "Coria C.F.",
      "goles_local": 1,
      "goles_visitante": 0,
      "estado": "jugado"
    },
    {
      "fixture_id": "QR7GKJN9",
      "jornada": 3,
      "fecha": "2025-09-21",
      "local": 7,
      "local_nombre": "Ciudad de Lucena",
      "visitante": 8,
      "visitante_nombre": "Conil",
      "goles_local": 4,
      "goles_visitante": 1,
      "estado": "jugado"
    },
    {
      "fixture_id": "neybXd7F",
      "jornada": 3,
      "fecha": "2025-09-21",
      "local": 13,
      "local_nombre": "Pozoblanco",
      "visitante": 5,
      "visitante_nombre": "Castilleja",
      "goles_local": 1,
      "goles_visitante": 0,
      "estado": "jugado"
    },
    {
      "fixture_id": "I148Mugc",
      "jornada": 3,
      "fecha": "2025-09-21",
      "local": 10,
      "local_nombre": "Cádiz B",
      "visitante": 3,
      "visitante_nombre": "Atletico Central",
      "goles_local": 1,
      "goles_visitante": 1,
      "estado": "jugado"
    },
    {
      "fixture_id": "zwuOETZj",
      "jornada": 3,
      "fecha": "2025-09-21",
      "local": 12,
      "local_nombre": "Dos Hermanas",
      "visitante": 18,
      "visitante_nombre": "Utrera",
      "goles_local": 2,
      "goles_visitante": 0,
      "estado": "jugado"
    },
    {
      "fixture_id": "271fDyGq",
      "jornada": 3,
      "fecha": "2025-09-21",
      "local": 16,
      "local_nombre": "Sevilla C",
      "visitante": 11,
      "visitante_nombre": "Córdoba B",
      "goles_local": 1,
      "goles_visitante": 2,
      "estado": "jugado"
    },
    {
      "fixture_id": "WpbVElil",
      "jornada": 3,
      "fecha": "2025-09-21",
      "local": 17,
      "local_nombre": "Tomares",
      "visitante": 15,
      "visitante_nombre": "San Roque de Lepe",
      "goles_local": 1,
      "goles_visitante": 1,
      "estado": "jugado"
    },
    {
      "fixture_id": "63CDRRzf",
      "jornada": 4,
      "fecha": "2025-09-27",
      "local": 11,
      "local_nombre": "Córdoba B",
      "visitante": 4,
      "visitante_nombre": "Bollullos",
      "goles_local": 0,
      "goles_visitante": 1,
      "estado": "jugado"
    },
    {
      "fixture_id": "ETFLP556",
      "jornada": 4,
      "fecha": "2025-09-27",
      "local": 1,
      "local_nombre": "AD Ceuta B",
      "visitante": 16,
      "visitante_nombre": "Sevilla C",
      "goles_local": 1,
      "goles_visitante": 0,
      "estado": "jugado"
    },
    {
      "fixture_id": "WKEvtRkm",
      "jornada": 4,
      "fecha": "2025-09-28",
      "local": 15,
      "local_nombre": "San Roque de Lepe",
      "visitante": 13,
      "visitante_nombre": "Pozoblanco",
      "goles_local": 0,
      "goles_visitante": 0,
      "estado": "jugado"
    },
    {
      "fixture_id": "0QknB6jD",
      "jornada": 4,
      "fecha": "2025-09-28",
      "local": 3,
      "local_nombre": "Atletico Central",
      "visitante": 12,
      "visitante_nombre": "Dos Hermanas",
      "goles_local": 3,
      "goles_visitante": 1,
      "estado": "jugado"
    },
    {
      "fixture_id": "2kdGomSP",
      "jornada": 4,
      "fecha": "2025-09-28",
      "local": 5,
      "local_nombre": "Castilleja",
      "visitante": 2,
      "visitante_nombre": "Atl. Onubense",
      "goles_local": 0,
      "goles_visitante": 3,
      "estado": "jugado"
    },
    {
      "fixture_id": "plO4Tm6s",
      "jornada": 4,
      "fecha": "2025-09-28",
      "local": 6,
      "local_nombre": "Chiclana",
      "visitante": 7,
      "visitante_nombre": "Ciudad de Lucena",
      "goles_local": 3,
      "goles_visitante": 1,
      "estado": "jugado"
    },
    {
      "fixture_id": "GYXYY9rK",
      "jornada": 4,
      "fecha": "2025-09-28",
      "local": 8,
      "local_nombre": "Conil",
      "visitante": 10,
      "visitante_nombre": "Cádiz B",
      "goles_local": 0,
      "goles_visitante": 2,
      "estado": "jugado"
    },
    {
      "fixture_id": "Ae9UNqzJ",
      "jornada": 4,
      "fecha": "2025-09-28",
      "local": 9,
      "local_nombre": "Coria C.F.",
      "visitante": 14,
      "visitante_nombre": "RB Linense",
      "goles_local": 1,
      "goles_visitante": 2,
      "estado": "jugado"
    },
    {
      "fixture_id": "SCivDSL0",
      "jornada": 4,
      "fecha": "2025-09-28",
      "local": 18,
      "local_nombre": "Utrera",
      "visitante": 17,
      "visitante_nombre": "Tomares",
      "goles_local": 2,
      "goles_visitante": 0,
      "estado": "jugado"
    },
    {
      "fixture_id": "IywMh4Zh",
      "jornada": 5,
      "fecha": "2025-10-04",
      "local": 4,
      "local_nombre": "Bollullos",
      "visitante": 1,
      "visitante_nombre": "AD Ceuta B",
      "goles_local": 0,
      "goles_visitante": 1,
      "estado": "jugado"
    },
    {
      "fixture_id": "pOvEfQ4t",
      "jornada": 5,
      "fecha": "2025-10-05",
      "local": 7,
      "local_nombre": "Ciudad de Lucena",
      "visitante": 11,
      "visitante_nombre": "Córdoba B",
      "goles_local": 1,
      "goles_visitante": 0,
      "estado": "jugado"
    },
    {
      "fixture_id": "MTZxkMYH",
      "jornada": 5,
      "fecha": "2025-10-05",
      "local": 14,
      "local_nombre": "RB Linense",
      "visitante": 5,
      "visitante_nombre": "Castilleja",
      "goles_local": 3,
      "goles_visitante": 0,
      "estado": "jugado"
    },
    {
      "fixture_id": "rqOom03U",
      "jornada": 5,
      "fecha": "2025-10-05",
      "local": 2,
      "local_nombre": "Atl. Onubense",
      "visitante": 15,
      "visitante_nombre": "San Roque de Lepe",
      "goles_local": 1,
      "goles_visitante": 1,
      "estado": "jugado"
    },
    {
      "fixture_id": "8Q93zNJO",
      "jornada": 5,
      "fecha": "2025-10-05",
      "local": 10,
      "local_nombre": "Cádiz B",
      "visitante": 6,
      "visitante_nombre": "Chiclana",
      "goles_local": 1,
      "goles_visitante": 1,
      "estado": "jugado"
    },
    {
      "fixture_id": "006exqkC",
      "jornada": 5,
      "fecha": "2025-10-05",
      "local": 12,
      "local_nombre": "Dos Hermanas",
      "visitante": 8,
      "visitante_nombre": "Conil",
      "goles_local": 1,
      "goles_visitante": 2,
      "estado": "jugado"
    },
    {
      "fixture_id": "E3WUjr45",
      "jornada": 5,
      "fecha": "2025-10-05",
      "local": 16,
      "local_nombre": "Sevilla C",
      "visitante": 9,
      "visitante_nombre": "Coria C.F.",
      "goles_local": 0,
      "goles_visitante": 0,
      "estado": "jugado"
    },
    {
      "fixture_id": "Cbbe73ln",
      "jornada": 5,
      "fecha": "2025-10-05",
      "local": 17,
      "local_nombre": "Tomares",
      "visitante": 13,
      "visitante_nombre": "Pozoblanco",
      "goles_local": 0,
      "goles_visitante": 3,
      "estado": "jugado"
    },
    {
      "fixture_id": "voInv5Ka",
      "jornada": 5,
      "fecha": "2025-10-05",
      "local": 18,
      "local_nombre": "Utrera",
      "visitante": 3,
      "visitante_nombre": "Atletico Central",
      "goles_local": 0,
      "goles_visitante": 0,
      "estado": "jugado"
    },
    {
      "fixture_id": "SnQiqi2d",
      "jornada": 6,
      "fecha": "2025-10-11",
      "local": 11,
      "local_nombre": "Córdoba B",
      "visitante": 10,
      "visitante_nombre": "Cádiz B",
      "goles_local": 0,
      "goles_visitante": 0,
      "estado": "jugado"
    },
    {
      "fixture_id": "S81SeUo2",
      "jornada": 6,
      "fecha": "2025-10-12",
      "local": 13,
      "local_nombre": "Pozoblanco",
      "visitante": 2,
      "visitante_nombre": "Atl. Onubense",
      "goles_local": 1,
      "goles_visitante": 1,
      "estado": "jugado"
    },
    {
      "fixture_id": "8r3v7ff3",
      "jornada": 6,
      "fecha": "2025-10-12",
      "local": 1,
      "local_nombre": "AD Ceuta B",
      "visitante": 7,
      "visitante_nombre": "Ciudad de Lucena",
      "goles_local": 1,
      "goles_visitante": 1,
      "estado": "jugado"
    },
    {
      "fixture_id": "86oRcjHk",
      "jornada": 6,
      "fecha": "2025-10-12",
      "local": 15,
      "local_nombre": "San Roque de Lepe",
      "visitante": 14,
      "visitante_nombre": "RB Linense",
      "goles_local": 1,
      "goles_visitante": 1,
      "estado": "jugado"
    },
    {
      "fixture_id": "8Qi45sJb",
      "jornada": 6,
      "fecha": "2025-10-12",
      "local": 3,
      "local_nombre": "Atletico Central",
      "visitante": 17,
      "visitante_nombre": "Tomares",
      "goles_local": 1,
      "goles_visitante": 1,
      "estado": "jugado"
    },
    {
      "fixture_id": "Cz0e3CgS",
      "jornada": 6,
      "fecha": "2025-10-12",
      "local": 5,
      "local_nombre": "Castilleja",
      "visitante": 16,
      "visitante_nombre": "Sevilla C",
      "goles_local": 2,
      "goles_visitante": 0,
      "estado": "jugado"
    },
    {
      "fixture_id": "zu8poDXq",
      "jornada": 6,
      "fecha": "2025-10-12",
      "local": 6,
      "local_nombre": "Chiclana",
      "visitante": 12,
      "visitante_nombre": "Dos Hermanas",
      "goles_local": 0,
      "goles_visitante": 0,
      "estado": "jugado"
    },
    {
      "fixture_id": "tvjC3LmB",
      "jornada": 6,
      "fecha": "2025-10-12",
      "local": 8,
      "local_nombre": "Conil",
      "visitante": 18,
      "visitante_nombre": "Utrera",
      "goles_local": 4,
      "goles_visitante": 2,
      "estado": "jugado"
    },
    {
      "fixture_id": "G86n5YOF",
      "jornada": 6,
      "fecha": "2025-10-12",
      "local": 9,
      "local_nombre": "Coria C.F.",
      "visitante": 4,
      "visitante_nombre": "Bollullos",
      "goles_local": 1,
      "goles_visitante": 4,
      "estado": "jugado"
    },
    {
      "fixture_id": "nDYhCkWr",
      "jornada": 7,
      "fecha": "2025-10-18",
      "local": 12,
      "local_nombre": "Dos Hermanas",
      "visitante": 11,
      "visitante_nombre": "Córdoba B",
      "goles_local": 0,
      "goles_visitante": 2,
      "estado": "jugado"
    },
    {
      "fixture_id": "UX7dWANE",
      "jornada": 7,
      "fecha": "2025-10-19",
      "local": 4,
      "local_nombre": "Bollullos",
      "visitante": 5,
      "visitante_nombre": "Castilleja",
      "goles_local": 1,
      "goles_visitante": 0,
      "estado": "jugado"
    },
    {
      "fixture_id": "EPP987V7",
      "jornada": 7,
      "fecha": "2025-10-19",
      "local": 7,
      "local_nombre": "Ciudad de Lucena",
      "visitante": 9,
      "visitante_nombre": "Coria C.F.",
      "goles_local": 5,
      "goles_visitante": 0,
      "estado": "jugado"
    },
    {
      "fixture_id": "tCR1AT0e",
      "jornada": 7,
      "fecha": "2025-10-19",
      "local": 10,
      "local_nombre": "Cádiz B",
      "visitante": 1,
      "visitante_nombre": "AD Ceuta B",
      "goles_local": 2,
      "goles_visitante": 2,
      "estado": "jugado"
    },
    {
      "fixture_id": "xbB4UlhR",
      "jornada": 7,
      "fecha": "2025-10-19",
      "local": 16,
      "local_nombre": "Sevilla C",
      "visitante": 15,
      "visitante_nombre": "San Roque de Lepe",
      "goles_local": 2,
      "goles_visitante": 3,
      "estado": "jugado"
    },
    {
      "fixture_id": "fFgEJXw9",
      "jornada": 7,
      "fecha": "2025-10-19",
      "local": 3,
      "local_nombre": "Atletico Central",
      "visitante": 8,
      "visitante_nombre": "Conil",
      "goles_local": 2,
      "goles_visitante": 0,
      "estado": "jugado"
    },
    {
      "fixture_id": "MVnyPSFl",
      "jornada": 7,
      "fecha": "2025-10-19",
      "local": 14,
      "local_nombre": "RB Linense",
      "visitante": 13,
      "visitante_nombre": "Pozoblanco",
      "goles_local": 2,
      "goles_visitante": 0,
      "estado": "jugado"
    },
    {
      "fixture_id": "fc0rN6p1",
      "jornada": 7,
      "fecha": "2025-10-19",
      "local": 17,
      "local_nombre": "Tomares",
      "visitante": 2,
      "visitante_nombre": "Atl. Onubense",
      "goles_local": 3,
      "goles_visitante": 1,
      "estado": "jugado"
    },
    {
      "fixture_id": "GUsNHB8L",
      "jornada": 7,
      "fecha": "2025-10-19",
      "local": 18,
      "local_nombre": "Utrera",
      "visitante": 6,
      "visitante_nombre": "Chiclana",
      "goles_local": 0,
      "goles_visitante": 1,
      "estado": "jugado"
    },
    {
      "fixture_id": "80QHy6af",
      "jornada": 8,
      "fecha": "2025-10-25",
      "local": 1,
      "local_nombre": "AD Ceuta B",
      "visitante": 12,
      "visitante_nombre": "Dos Hermanas",
      "goles_local": 1,
      "goles_visitante": 0,
      "estado": "jugado"
    },
    {
      "fixture_id": "p6PiL5WA",
      "jornada": 8,
      "fecha": "2025-10-25",
      "local": 2,
      "local_nombre": "Atl. Onubense",
      "visitante": 14,
      "visitante_nombre": "RB Linense",
      "goles_local": 0,
      "goles_visitante": 0,
      "estado": "jugado"
    },
    {
      "fixture_id": "Q39jNR1b",
      "jornada": 8,
      "fecha": "2025-10-26",
      "local": 13,
      "local_nombre": "Pozoblanco",
      "visitante": 16,
      "visitante_nombre": "Sevilla C",
      "goles_local": 3,
      "goles_visitante": 2,
      "estado": "jugado"
    },
    {
      "fixture_id": "rJtwql7K",
      "jornada": 8,
      "fecha": "2025-10-26",
      "local": 6,
      "local_nombre": "Chiclana",
      "visitante": 3,
      "visitante_nombre": "Atletico Central",
      "goles_local": 0,
      "goles_visitante": 2,
      "estado": "jugado"
    },
    {
      "fixture_id": "xtIYXNbJ",
      "jornada": 8,
      "fecha": "2025-10-26",
      "local": 5,
      "local_nombre": "Castilleja",
      "visitante": 7,
      "visitante_nombre": "Ciudad de Lucena",
      "goles_local": 0,
      "goles_visitante": 2,
      "estado": "jugado"
    },
    {
      "fixture_id": "jPgiLpFD",
      "jornada": 8,
      "fecha": "2025-10-26",
      "local": 8,
      "local_nombre": "Conil",
      "visitante": 17,
      "visitante_nombre": "Tomares",
      "goles_local": 2,
      "goles_visitante": 0,
      "estado": "jugado"
    },
    {
      "fixture_id": "23N9wSUs",
      "jornada": 8,
      "fecha": "2025-10-26",
      "local": 11,
      "local_nombre": "Córdoba B",
      "visitante": 18,
      "visitante_nombre": "Utrera",
      "goles_local": 2,
      "goles_visitante": 0,
      "estado": "jugado"
    },
    {
      "fixture_id": "UFEQZqU6",
      "jornada": 8,
      "fecha": "2025-10-26",
      "local": 9,
      "local_nombre": "Coria C.F.",
      "visitante": 10,
      "visitante_nombre": "Cádiz B",
      "goles_local": 0,
      "goles_visitante": 2,
      "estado": "jugado"
    },
    {
      "fixture_id": "hjBrPmXo",
      "jornada": 8,
      "fecha": "2025-10-26",
      "local": 15,
      "local_nombre": "San Roque de Lepe",
      "visitante": 4,
      "visitante_nombre": "Bollullos",
      "goles_local": 0,
      "goles_visitante": 2,
      "estado": "jugado"
    },
    {
      "fixture_id": "4AdIyRGi",
      "jornada": 9,
      "fecha": "2025-11-01",
      "local": 18,
      "local_nombre": "Utrera",
      "visitante": 1,
      "visitante_nombre": "AD Ceuta B",
      "goles_local": 3,
      "goles_visitante": 2,
      "estado": "jugado"
    },
    {
      "fixture_id": "EadsWMpT",
      "jornada": 9,
      "fecha": "2025-11-02",
      "local": 7,
      "local_nombre": "Ciudad de Lucena",
      "visitante": 15,
      "visitante_nombre": "San Roque de Lepe",
      "goles_local": 1,
      "goles_visitante": 1,
      "estado": "jugado"
    },
    {
      "fixture_id": "prmDQ08j",
      "jornada": 9,
      "fecha": "2025-11-02",
      "local": 4,
      "local_nombre": "Bollullos",
      "visitante": 13,
      "visitante_nombre": "Pozoblanco",
      "goles_local": 3,
      "goles_visitante": 0,
      "estado": "jugado"
    },
    {
      "fixture_id": "hWSaJq1N",
      "jornada": 9,
      "fecha": "2025-11-02",
      "local": 8,
      "local_nombre": "Conil",
      "visitante": 6,
      "visitante_nombre": "Chiclana",
      "goles_local": 2,
      "goles_visitante": 0,
      "estado": "jugado"
    },
    {
      "fixture_id": "QwQal40c",
      "jornada": 9,
      "fecha": "2025-11-02",
      "local": 16,
      "local_nombre": "Sevilla C",
      "visitante": 2,
      "visitante_nombre": "Atl. Onubense",
      "goles_local": 0,
      "goles_visitante": 2,
      "estado": "jugado"
    },
    {
      "fixture_id": "x44WDNOp",
      "jornada": 9,
      "fecha": "2025-11-02",
      "local": 3,
      "local_nombre": "Atletico Central",
      "visitante": 11,
      "visitante_nombre": "Córdoba B",
      "goles_local": 2,
      "goles_visitante": 5,
      "estado": "jugado"
    },
    {
      "fixture_id": "IX2YXrGG",
      "jornada": 9,
      "fecha": "2025-11-02",
      "local": 10,
      "local_nombre": "Cádiz B",
      "visitante": 5,
      "visitante_nombre": "Castilleja",
      "goles_local": 7,
      "goles_visitante": 1,
      "estado": "jugado"
    },
    {
      "fixture_id": "pK4QZ4o4",
      "jornada": 9,
      "fecha": "2025-11-02",
      "local": 12,
      "local_nombre": "Dos Hermanas",
      "visitante": 9,
      "visitante_nombre": "Coria C.F.",
      "goles_local": 1,
      "goles_visitante": 0,
      "estado": "jugado"
    },
    {
      "fixture_id": "CfO7nrV9",
      "jornada": 9,
      "fecha": "2025-11-02",
      "local": 17,
      "local_nombre": "Tomares",
      "visitante": 14,
      "visitante_nombre": "RB Linense",
      "goles_local": 0,
      "goles_visitante": 3,
      "estado": "jugado"
    },
    {
      "fixture_id": "0Kdewvhd",
      "jornada": 10,
      "fecha": "2025-11-08",
      "local": 1,
      "local_nombre": "AD Ceuta B",
      "visitante": 3,
      "visitante_nombre": "Atletico Central",
      "goles_local": 2,
      "goles_visitante": 1,
      "estado": "jugado"
    },
    {
      "fixture_id": "nyLxjHy2",
      "jornada": 10,
      "fecha": "2025-11-08",
      "local": 2,
      "local_nombre": "Atl. Onubense",
      "visitante": 4,
      "visitante_nombre": "Bollullos",
      "goles_local": 1,
      "goles_visitante": 3,
      "estado": "jugado"
    },
    {
      "fixture_id": "fwtbcaqS",
      "jornada": 10,
      "fecha": "2025-11-09",
      "local": 15,
      "local_nombre": "San Roque de Lepe",
      "visitante": 10,
      "visitante_nombre": "Cádiz B",
      "goles_local": 0,
      "goles_visitante": 2,
      "estado": "jugado"
    },
    {
      "fixture_id": "ENMUiw7k",
      "jornada": 10,
      "fecha": "2025-11-09",
      "local": 13,
      "local_nombre": "Pozoblanco",
      "visitante": 7,
      "visitante_nombre": "Ciudad de Lucena",
      "goles_local": 0,
      "goles_visitante": 0,
      "estado": "jugado"
    },
    {
      "fixture_id": "CUvHDKT8",
      "jornada": 10,
      "fecha": "2025-11-09",
      "local": 14,
      "local_nombre": "RB Linense",
      "visitante": 16,
      "visitante_nombre": "Sevilla C",
      "goles_local": 2,
      "goles_visitante": 1,
      "estado": "jugado"
    },
    {
      "fixture_id": "nDxjaLEF",
      "jornada": 10,
      "fecha": "2025-11-09",
      "local": 5,
      "local_nombre": "Castilleja",
      "visitante": 12,
      "visitante_nombre": "Dos Hermanas",
      "goles_local": 1,
      "goles_visitante": 2,
      "estado": "jugado"
    },
    {
      "fixture_id": "8MHGpMaM",
      "jornada": 10,
      "fecha": "2025-11-09",
      "local": 6,
      "local_nombre": "Chiclana",
      "visitante": 17,
      "visitante_nombre": "Tomares",
      "goles_local": 2,
      "goles_visitante": 0,
      "estado": "jugado"
    },
    {
      "fixture_id": "4h3nu0Nq",
      "jornada": 10,
      "fecha": "2025-11-09",
      "local": 11,
      "local_nombre": "Córdoba B",
      "visitante": 8,
      "visitante_nombre": "Conil",
      "goles_local": 1,
      "goles_visitante": 1,
      "estado": "jugado"
    },
    {
      "fixture_id": "Qcls1sp3",
      "jornada": 10,
      "fecha": "2025-11-09",
      "local": 9,
      "local_nombre": "Coria C.F.",
      "visitante": 18,
      "visitante_nombre": "Utrera",
      "goles_local": 3,
      "goles_visitante": 0,
      "estado": "jugado"
    },
    {
      "fixture_id": "vqecgjrf",
      "jornada": 11,
      "fecha": "2025-11-15",
      "local": 8,
      "local_nombre": "Conil",
      "visitante": 1,
      "visitante_nombre": "AD Ceuta B",
      "goles_local": 0,
      "goles_visitante": 2,
      "estado": "jugado"
    },
    {
      "fixture_id": "0COv6TRa",
      "jornada": 11,
      "fecha": "2025-11-16",
      "local": 7,
      "local_nombre": "Ciudad de Lucena",
      "visitante": 2,
      "visitante_nombre": "Atl. Onubense",
      "goles_local": 2,
      "goles_visitante": 0,
      "estado": "jugado"
    },
    {
      "fixture_id": "MRCm47dC",
      "jornada": 11,
      "fecha": "2025-11-16",
      "local": 4,
      "local_nombre": "Bollullos",
      "visitante": 14,
      "visitante_nombre": "RB Linense",
      "goles_local": 0,
      "goles_visitante": 0,
      "estado": "jugado"
    },
    {
      "fixture_id": "n9b5iUC6",
      "jornada": 11,
      "fecha": "2025-11-16",
      "local": 3,
      "local_nombre": "Atletico Central",
      "visitante": 9,
      "visitante_nombre": "Coria C.F.",
      "goles_local": 3,
      "goles_visitante": 0,
      "estado": "jugado"
    },
    {
      "fixture_id": "hnLW7kcm",
      "jornada": 11,
      "fecha": "2025-11-16",
      "local": 10,
      "local_nombre": "Cádiz B",
      "visitante": 13,
      "visitante_nombre": "Pozoblanco",
      "goles_local": 0,
      "goles_visitante": 0,
      "estado": "jugado"
    },
    {
      "fixture_id": "IT6leCDs",
      "jornada": 11,
      "fecha": "2025-11-16",
      "local": 6,
      "local_nombre": "Chiclana",
      "visitante": 11,
      "visitante_nombre": "Córdoba B",
      "goles_local": 4,
      "goles_visitante": 1,
      "estado": "jugado"
    },
    {
      "fixture_id": "Y1v0DBZP",
      "jornada": 11,
      "fecha": "2025-11-16",
      "local": 12,
      "local_nombre": "Dos Hermanas",
      "visitante": 15,
      "visitante_nombre": "San Roque de Lepe",
      "goles_local": 3,
      "goles_visitante": 1,
      "estado": "jugado"
    },
    {
      "fixture_id": "8rBe2oRO",
      "jornada": 11,
      "fecha": "2025-11-16",
      "local": 17,
      "local_nombre": "Tomares",
      "visitante": 16,
      "visitante_nombre": "Sevilla C",
      "goles_local": 1,
      "goles_visitante": 3,
      "estado": "jugado"
    },
    {
      "fixture_id": "t8iEk8sJ",
      "jornada": 11,
      "fecha": "2025-11-16",
      "local": 18,
      "local_nombre": "Utrera",
      "visitante": 5,
      "visitante_nombre": "Castilleja",
      "goles_local": 2,
      "goles_visitante": 2,
      "estado": "jugado"
    },
    {
      "fixture_id": "KMvEKStg",
      "jornada": 12,
      "fecha": "2025-11-22",
      "local": 1,
      "local_nombre": "AD Ceuta B",
      "visitante": 6,
      "visitante_nombre": "Chiclana",
      "goles_local": 3,
      "goles_visitante": 1,
      "estado": "jugado"
    },
    {
      "fixture_id": "G2DeX5Qb",
      "jornada": 12,
      "fecha": "2025-11-22",
      "local": 2,
      "local_nombre": "Atl. Onubense",
      "visitante": 10,
      "visitante_nombre": "Cádiz B",
      "goles_local": 1,
      "goles_visitante": 2,
      "estado": "jugado"
    },
    {
      "fixture_id": "UBvwFOAU",
      "jornada": 12,
      "fecha": "2025-11-23",
      "local": 15,
      "local_nombre": "San Roque de Lepe",
      "visitante": 18,
      "visitante_nombre": "Utrera",
      "goles_local": 2,
      "goles_visitante": 1,
      "estado": "jugado"
    },
    {
      "fixture_id": "8djUGptI",
      "jornada": 12,
      "fecha": "2025-11-23",
      "local": 5,
      "local_nombre": "Castilleja",
      "visitante": 3,
      "visitante_nombre": "Atletico Central",
      "goles_local": 0,
      "goles_visitante": 1,
      "estado": "jugado"
    },
    {
      "fixture_id": "n9t6MlCt",
      "jornada": 12,
      "fecha": "2025-11-23",
      "local": 11,
      "local_nombre": "Córdoba B",
      "visitante": 17,
      "visitante_nombre": "Tomares",
      "goles_local": 1,
      "goles_visitante": 2,
      "estado": "jugado"
    },
    {
      "fixture_id": "GlYMI6B5",
      "jornada": 12,
      "fecha": "2025-11-23",
      "local": 9,
      "local_nombre": "Coria C.F.",
      "visitante": 8,
      "visitante_nombre": "Conil",
      "goles_local": 0,
      "goles_visitante": 1,
      "estado": "jugado"
    },
    {
      "fixture_id": "lGB3VqeB",
      "jornada": 12,
      "fecha": "2025-11-23",
      "local": 14,
      "local_nombre": "RB Linense",
      "visitante": 7,
      "visitante_nombre": "Ciudad de Lucena",
      "goles_local": 0,
      "goles_visitante": 0,
      "estado": "jugado"
    },
    {
      "fixture_id": "8IR4TNPN",
      "jornada": 12,
      "fecha": "2025-11-23",
      "local": 16,
      "local_nombre": "Sevilla C",
      "visitante": 4,
      "visitante_nombre": "Bollullos",
      "goles_local": 3,
      "goles_visitante": 1,
      "estado": "jugado"
    },
    {
      "fixture_id": "KzKnZRen",
      "jornada": 12,
      "fecha": "2025-12-03",
      "local": 13,
      "local_nombre": "Pozoblanco",
      "visitante": 12,
      "visitante_nombre": "Dos Hermanas",
      "goles_local": 3,
      "goles_visitante": 4,
      "estado": "jugado"
    },
    {
      "fixture_id": "MLivrNvH",
      "jornada": 13,
      "fecha": "2025-12-06",
      "local": 3,
      "local_nombre": "Atletico Central",
      "visitante": 15,
      "visitante_nombre": "San Roque de Lepe",
      "goles_local": 1,
      "goles_visitante": 3,
      "estado": "jugado"
    },
    {
      "fixture_id": "v1IzO1mo",
      "jornada": 13,
      "fecha": "2025-12-06",
      "local": 11,
      "local_nombre": "Córdoba B",
      "visitante": 1,
      "visitante_nombre": "AD Ceuta B",
      "goles_local": 3,
      "goles_visitante": 0,
      "estado": "jugado"
    },
    {
      "fixture_id": "SMbVqqA4",
      "jornada": 13,
      "fecha": "2025-12-06",
      "local": 8,
      "local_nombre": "Conil",
      "visitante": 5,
      "visitante_nombre": "Castilleja",
      "goles_local": 2,
      "goles_visitante": 2,
      "estado": "jugado"
    },
    {
      "fixture_id": "xdlFqzGL",
      "jornada": 13,
      "fecha": "2025-12-07",
      "local": 7,
      "local_nombre": "Ciudad de Lucena",
      "visitante": 16,
      "visitante_nombre": "Sevilla C",
      "goles_local": 1,
      "goles_visitante": 0,
      "estado": "jugado"
    },
    {
      "fixture_id": "Gt06odo9",
      "jornada": 13,
      "fecha": "2025-12-07",
      "local": 10,
      "local_nombre": "Cádiz B",
      "visitante": 14,
      "visitante_nombre": "RB Linense",
      "goles_local": 0,
      "goles_visitante": 4,
      "estado": "jugado"
    },
    {
      "fixture_id": "KdeNo5uh",
      "jornada": 13,
      "fecha": "2025-12-07",
      "local": 6,
      "local_nombre": "Chiclana",
      "visitante": 9,
      "visitante_nombre": "Coria C.F.",
      "goles_local": 2,
      "goles_visitante": 1,
      "estado": "jugado"
    },
    {
      "fixture_id": "lz8KNhg2",
      "jornada": 13,
      "fecha": "2025-12-07",
      "local": 12,
      "local_nombre": "Dos Hermanas",
      "visitante": 2,
      "visitante_nombre": "Atl. Onubense",
      "goles_local": 2,
      "goles_visitante": 0,
      "estado": "jugado"
    },
    {
      "fixture_id": "YukpvEwq",
      "jornada": 13,
      "fecha": "2025-12-07",
      "local": 17,
      "local_nombre": "Tomares",
      "visitante": 4,
      "visitante_nombre": "Bollullos",
      "goles_local": 0,
      "goles_visitante": 1,
      "estado": "jugado"
    },
    {
      "fixture_id": "h8EBPEOk",
      "jornada": 13,
      "fecha": "2025-12-07",
      "local": 18,
      "local_nombre": "Utrera",
      "visitante": 13,
      "visitante_nombre": "Pozoblanco",
      "goles_local": 2,
      "goles_visitante": 1,
      "estado": "jugado"
    },
    {
      "fixture_id": "EJnsXHmD",
      "jornada": 14,
      "fecha": "2025-12-14",
      "local": 14,
      "local_nombre": "RB Linense",
      "visitante": 12,
      "visitante_nombre": "Dos Hermanas",
      "goles_local": 2,
      "goles_visitante": 2,
      "estado": "jugado"
    },
    {
      "fixture_id": "lYxhka3s",
      "jornada": 14,
      "fecha": "2025-12-14",
      "local": 4,
      "local_nombre": "Bollullos",
      "visitante": 7,
      "visitante_nombre": "Ciudad de Lucena",
      "goles_local": 0,
      "goles_visitante": 0,
      "estado": "jugado"
    },
    {
      "fixture_id": "IigYYwJ0",
      "jornada": 14,
      "fecha": "2025-12-14",
      "local": 2,
      "local_nombre": "Atl. Onubense",
      "visitante": 18,
      "visitante_nombre": "Utrera",
      "goles_local": 3,
      "goles_visitante": 1,
      "estado": "jugado"
    },
    {
      "fixture_id": "KdBorrdE",
      "jornada": 14,
      "fecha": "2025-12-14",
      "local": 5,
      "local_nombre": "Castilleja",
      "visitante": 6,
      "visitante_nombre": "Chiclana",
      "goles_local": 1,
      "goles_visitante": 1,
      "estado": "jugado"
    },
    {
      "fixture_id": "2Lt1zWx8",
      "jornada": 14,
      "fecha": "2025-12-14",
      "local": 9,
      "local_nombre": "Coria C.F.",
      "visitante": 11,
      "visitante_nombre": "Córdoba B",
      "goles_local": 1,
      "goles_visitante": 1,
      "estado": "jugado"
    },
    {
      "fixture_id": "ARkQz0ll",
      "jornada": 14,
      "fecha": "2025-12-14",
      "local": 13,
      "local_nombre": "Pozoblanco",
      "visitante": 3,
      "visitante_nombre": "Atletico Central",
      "goles_local": 1,
      "goles_visitante": 2,
      "estado": "jugado"
    },
    {
      "fixture_id": "QgEgtMQQ",
      "jornada": 14,
      "fecha": "2025-12-14",
      "local": 15,
      "local_nombre": "San Roque de Lepe",
      "visitante": 8,
      "visitante_nombre": "Conil",
      "goles_local": 1,
      "goles_visitante": 0,
      "estado": "jugado"
    },
    {
      "fixture_id": "6DZSfLuK",
      "jornada": 14,
      "fecha": "2025-12-14",
      "local": 16,
      "local_nombre": "Sevilla C",
      "visitante": 10,
      "visitante_nombre": "Cádiz B",
      "goles_local": 2,
      "goles_visitante": 1,
      "estado": "jugado"
    },
    {
      "fixture_id": "U7rgxh8e",
      "jornada": 14,
      "fecha": "2026-01-07",
      "local": 1,
      "local_nombre": "AD Ceuta B",
      "visitante": 17,
      "visitante_nombre": "Tomares",
      "goles_local": 2,
      "goles_visitante": 1,
      "estado": "jugado"
    },
    {
      "fixture_id": "QTU27bPP",
      "jornada": 15,
      "fecha": "2025-12-20",
      "local": 8,
      "local_nombre": "Conil",
      "visitante": 13,
      "visitante_nombre": "Pozoblanco",
      "goles_local": 1,
      "goles_visitante": 1,
      "estado": "jugado"
    },
    {
      "fixture_id": "jwD93kOi",
      "jornada": 15,
      "fecha": "2025-12-20",
      "local": 17,
      "local_nombre": "Tomares",
      "visitante": 7,
      "visitante_nombre": "Ciudad de Lucena",
      "goles_local": 0,
      "goles_visitante": 0,
      "estado": "jugado"
    },
    {
      "fixture_id": "dbt0mwYg",
      "jornada": 15,
      "fecha": "2025-12-20",
      "local": 1,
      "local_nombre": "AD Ceuta B",
      "visitante": 9,
      "visitante_nombre": "Coria C.F.",
      "goles_local": 2,
      "goles_visitante": 0,
      "estado": "jugado"
    },
    {
      "fixture_id": "QiDkbfnC",
      "jornada": 15,
      "fecha": "2025-12-20",
      "local": 12,
      "local_nombre": "Dos Hermanas",
      "visitante": 16,
      "visitante_nombre": "Sevilla C",
      "goles_local": 3,
      "goles_visitante": 0,
      "estado": "jugado"
    },
    {
      "fixture_id": "MaGY1xmm",
      "jornada": 15,
      "fecha": "2025-12-20",
      "local": 3,
      "local_nombre": "Atletico Central",
      "visitante": 2,
      "visitante_nombre": "Atl. Onubense",
      "goles_local": 1,
      "goles_visitante": 0,
      "estado": "jugado"
    },
    {
      "fixture_id": "ptQNunWp",
      "jornada": 15,
      "fecha": "2025-12-20",
      "local": 10,
      "local_nombre": "Cádiz B",
      "visitante": 4,
      "visitante_nombre": "Bollullos",
      "goles_local": 3,
      "goles_visitante": 0,
      "estado": "jugado"
    },
    {
      "fixture_id": "IDU8oH26",
      "jornada": 15,
      "fecha": "2025-12-20",
      "local": 11,
      "local_nombre": "Córdoba B",
      "visitante": 5,
      "visitante_nombre": "Castilleja",
      "goles_local": 0,
      "goles_visitante": 2,
      "estado": "jugado"
    },
    {
      "fixture_id": "QwYGqeXI",
      "jornada": 15,
      "fecha": "2025-12-21",
      "local": 6,
      "local_nombre": "Chiclana",
      "visitante": 15,
      "visitante_nombre": "San Roque de Lepe",
      "goles_local": 1,
      "goles_visitante": 0,
      "estado": "jugado"
    },
    {
      "fixture_id": "IR9s0GHa",
      "jornada": 15,
      "fecha": "2025-12-21",
      "local": 18,
      "local_nombre": "Utrera",
      "visitante": 14,
      "visitante_nombre": "RB Linense",
      "goles_local": 3,
      "goles_visitante": 3,
      "estado": "jugado"
    },
    {
      "fixture_id": "KI4Qa7NG",
      "jornada": 16,
      "fecha": "2026-01-03",
      "local": 5,
      "local_nombre": "Castilleja",
      "visitante": 1,
      "visitante_nombre": "AD Ceuta B",
      "goles_local": 3,
      "goles_visitante": 1,
      "estado": "jugado"
    },
    {
      "fixture_id": "QeRiGS7c",
      "jornada": 16,
      "fecha": "2026-01-04",
      "local": 2,
      "local_nombre": "Atl. Onubense",
      "visitante": 8,
      "visitante_nombre": "Conil",
      "goles_local": 2,
      "goles_visitante": 2,
      "estado": "jugado"
    },
    {
      "fixture_id": "WWvu52ad",
      "jornada": 16,
      "fecha": "2026-01-04",
      "local": 7,
      "local_nombre": "Ciudad de Lucena",
      "visitante": 10,
      "visitante_nombre": "Cádiz B",
      "goles_local": 3,
      "goles_visitante": 0,
      "estado": "jugado"
    },
    {
      "fixture_id": "QJ9v7OUq",
      "jornada": 16,
      "fecha": "2026-01-04",
      "local": 4,
      "local_nombre": "Bollullos",
      "visitante": 12,
      "visitante_nombre": "Dos Hermanas",
      "goles_local": 2,
      "goles_visitante": 1,
      "estado": "jugado"
    },
    {
      "fixture_id": "p0l5hPFj",
      "jornada": 16,
      "fecha": "2026-01-04",
      "local": 13,
      "local_nombre": "Pozoblanco",
      "visitante": 6,
      "visitante_nombre": "Chiclana",
      "goles_local": 2,
      "goles_visitante": 2,
      "estado": "jugado"
    },
    {
      "fixture_id": "GpbZcohT",
      "jornada": 16,
      "fecha": "2026-01-04",
      "local": 15,
      "local_nombre": "San Roque de Lepe",
      "visitante": 11,
      "visitante_nombre": "Córdoba B",
      "goles_local": 4,
      "goles_visitante": 1,
      "estado": "jugado"
    },
    {
      "fixture_id": "UmO8Cp7M",
      "jornada": 16,
      "fecha": "2026-01-04",
      "local": 16,
      "local_nombre": "Sevilla C",
      "visitante": 18,
      "visitante_nombre": "Utrera",
      "goles_local": 2,
      "goles_visitante": 1,
      "estado": "jugado"
    },
    {
      "fixture_id": "n56I1Th4",
      "jornada": 16,
      "fecha": "2026-01-04",
      "local": 17,
      "local_nombre": "Tomares",
      "visitante": 9,
      "visitante_nombre": "Coria C.F.",
      "goles_local": 5,
      "goles_visitante": 0,
      "estado": "jugado"
    },
    {
      "fixture_id": "YLUaE6xA",
      "jornada": 16,
      "fecha": "2026-01-14",
      "local": 14,
      "local_nombre": "RB Linense",
      "visitante": 3,
      "visitante_nombre": "Atletico Central",
      "goles_local": 1,
      "goles_visitante": 0,
      "estado": "jugado"
    },
    {
      "fixture_id": "KhLZQqMF",
      "jornada": 17,
      "fecha": "2026-01-10",
      "local": 1,
      "local_nombre": "AD Ceuta B",
      "visitante": 15,
      "visitante_nombre": "San Roque de Lepe",
      "goles_local": 0,
      "goles_visitante": 0,
      "estado": "jugado"
    },
    {
      "fixture_id": "Yeo9uqy9",
      "jornada": 17,
      "fecha": "2026-01-11",
      "local": 3,
      "local_nombre": "Atletico Central",
      "visitante": 16,
      "visitante_nombre": "Sevilla C",
      "goles_local": 1,
      "goles_visitante": 0,
      "estado": "jugado"
    },
    {
      "fixture_id": "CAOeWvbe",
      "jornada": 17,
      "fecha": "2026-01-11",
      "local": 10,
      "local_nombre": "Cádiz B",
      "visitante": 17,
      "visitante_nombre": "Tomares",
      "goles_local": 0,
      "goles_visitante": 1,
      "estado": "jugado"
    },
    {
      "fixture_id": "pz5EJ1Ek",
      "jornada": 17,
      "fecha": "2026-01-11",
      "local": 6,
      "local_nombre": "Chiclana",
      "visitante": 2,
      "visitante_nombre": "Atl. Onubense",
      "goles_local": 2,
      "goles_visitante": 1,
      "estado": "jugado"
    },
    {
      "fixture_id": "Im3MHuq2",
      "jornada": 17,
      "fecha": "2026-01-11",
      "local": 8,
      "local_nombre": "Conil",
      "visitante": 14,
      "visitante_nombre": "RB Linense",
      "goles_local": 0,
      "goles_visitante": 2,
      "estado": "jugado"
    },
    {
      "fixture_id": "SIOsPNjS",
      "jornada": 17,
      "fecha": "2026-01-11",
      "local": 11,
      "local_nombre": "Córdoba B",
      "visitante": 13,
      "visitante_nombre": "Pozoblanco",
      "goles_local": 1,
      "goles_visitante": 2,
      "estado": "jugado"
    },
    {
      "fixture_id": "bwXQS5i3",
      "jornada": 17,
      "fecha": "2026-01-11",
      "local": 9,
      "local_nombre": "Coria C.F.",
      "visitante": 5,
      "visitante_nombre": "Castilleja",
      "goles_local": 1,
      "goles_visitante": 1,
      "estado": "jugado"
    },
    {
      "fixture_id": "QgQmY0Tr",
      "jornada": 17,
      "fecha": "2026-01-11",
      "local": 12,
      "local_nombre": "Dos Hermanas",
      "visitante": 7,
      "visitante_nombre": "Ciudad de Lucena",
      "goles_local": 2,
      "goles_visitante": 4,
      "estado": "jugado"
    },
    {
      "fixture_id": "tMlHwN5L",
      "jornada": 17,
      "fecha": "2026-01-11",
      "local": 18,
      "local_nombre": "Utrera",
      "visitante": 4,
      "visitante_nombre": "Bollullos",
      "goles_local": 1,
      "goles_visitante": 0,
      "estado": "jugado"
    },
    {
      "fixture_id": "fo2clDJt",
      "jornada": 18,
      "fecha": "2026-01-17",
      "local": 1,
      "local_nombre": "AD Ceuta B",
      "visitante": 13,
      "visitante_nombre": "Pozoblanco",
      "goles_local": 0,
      "goles_visitante": 1,
      "estado": "jugado"
    },
    {
      "fixture_id": "GKWnU9YO",
      "jornada": 18,
      "fecha": "2026-01-17",
      "local": 11,
      "local_nombre": "Córdoba B",
      "visitante": 2,
      "visitante_nombre": "Atl. Onubense",
      "goles_local": 0,
      "goles_visitante": 1,
      "estado": "jugado"
    },
    {
      "fixture_id": "nuuWXiZa",
      "jornada": 18,
      "fecha": "2026-01-18",
      "local": 8,
      "local_nombre": "Conil",
      "visitante": 16,
      "visitante_nombre": "Sevilla C",
      "goles_local": 2,
      "goles_visitante": 0,
      "estado": "jugado"
    },
    {
      "fixture_id": "fXMOZD4m",
      "jornada": 18,
      "fecha": "2026-01-18",
      "local": 3,
      "local_nombre": "Atletico Central",
      "visitante": 4,
      "visitante_nombre": "Bollullos",
      "goles_local": 2,
      "goles_visitante": 0,
      "estado": "jugado"
    },
    {
      "fixture_id": "n1G6pVI5",
      "jornada": 18,
      "fecha": "2026-01-18",
      "local": 5,
      "local_nombre": "Castilleja",
      "visitante": 17,
      "visitante_nombre": "Tomares",
      "goles_local": 1,
      "goles_visitante": 0,
      "estado": "jugado"
    },
    {
      "fixture_id": "8fTvWV3C",
      "jornada": 18,
      "fecha": "2026-01-18",
      "local": 6,
      "local_nombre": "Chiclana",
      "visitante": 14,
      "visitante_nombre": "RB Linense",
      "goles_local": 2,
      "goles_visitante": 4,
      "estado": "jugado"
    },
    {
      "fixture_id": "Sb05nilg",
      "jornada": 18,
      "fecha": "2026-01-18",
      "local": 9,
      "local_nombre": "Coria C.F.",
      "visitante": 15,
      "visitante_nombre": "San Roque de Lepe",
      "goles_local": 1,
      "goles_visitante": 0,
      "estado": "jugado"
    },
    {
      "fixture_id": "8xI4UIS7",
      "jornada": 18,
      "fecha": "2026-01-18",
      "local": 12,
      "local_nombre": "Dos Hermanas",
      "visitante": 10,
      "visitante_nombre": "Cádiz B",
      "goles_local": 3,
      "goles_visitante": 0,
      "estado": "jugado"
    },
    {
      "fixture_id": "0W4jhMKE",
      "jornada": 18,
      "fecha": "2026-01-18",
      "local": 18,
      "local_nombre": "Utrera",
      "visitante": 7,
      "visitante_nombre": "Ciudad de Lucena",
      "goles_local": 2,
      "goles_visitante": 1,
      "estado": "jugado"
    },
    {
      "fixture_id": "Gt8NtmIU",
      "jornada": 19,
      "fecha": "2026-01-24",
      "local": 10,
      "local_nombre": "Cádiz B",
      "visitante": 18,
      "visitante_nombre": "Utrera",
      "goles_local": 2,
      "goles_visitante": 1,
      "estado": "jugado"
    },
    {
      "fixture_id": "65mX0j3n",
      "jornada": 19,
      "fecha": "2026-01-25",
      "local": 7,
      "local_nombre": "Ciudad de Lucena",
      "visitante": 3,
      "visitante_nombre": "Atletico Central",
      "goles_local": 2,
      "goles_visitante": 1,
      "estado": "jugado"
    },
    {
      "fixture_id": "04ttaUXb",
      "jornada": 19,
      "fecha": "2026-01-25",
      "local": 4,
      "local_nombre": "Bollullos",
      "visitante": 8,
      "visitante_nombre": "Conil",
      "goles_local": 1,
      "goles_visitante": 1,
      "estado": "jugado"
    },
    {
      "fixture_id": "rilDcxEi",
      "jornada": 19,
      "fecha": "2026-01-25",
      "local": 13,
      "local_nombre": "Pozoblanco",
      "visitante": 9,
      "visitante_nombre": "Coria C.F.",
      "goles_local": 1,
      "goles_visitante": 1,
      "estado": "jugado"
    },
    {
      "fixture_id": "0SOSkQfo",
      "jornada": 19,
      "fecha": "2026-01-25",
      "local": 2,
      "local_nombre": "Atl. Onubense",
      "visitante": 1,
      "visitante_nombre": "AD Ceuta B",
      "goles_local": 2,
      "goles_visitante": 0,
      "estado": "jugado"
    },
    {
      "fixture_id": "YHvlc82B",
      "jornada": 19,
      "fecha": "2026-01-25",
      "local": 16,
      "local_nombre": "Sevilla C",
      "visitante": 6,
      "visitante_nombre": "Chiclana",
      "goles_local": 1,
      "goles_visitante": 1,
      "estado": "jugado"
    },
    {
      "fixture_id": "UqYdenXN",
      "jornada": 19,
      "fecha": "2026-01-25",
      "local": 14,
      "local_nombre": "RB Linense",
      "visitante": 11,
      "visitante_nombre": "Córdoba B",
      "goles_local": 2,
      "goles_visitante": 1,
      "estado": "jugado"
    },
    {
      "fixture_id": "GI1KeGr4",
      "jornada": 19,
      "fecha": "2026-01-25",
      "local": 15,
      "local_nombre": "San Roque de Lepe",
      "visitante": 5,
      "visitante_nombre": "Castilleja",
      "goles_local": 2,
      "goles_visitante": 0,
      "estado": "jugado"
    },
    {
      "fixture_id": "fRJEr9mI",
      "jornada": 19,
      "fecha": "2026-01-25",
      "local": 17,
      "local_nombre": "Tomares",
      "visitante": 12,
      "visitante_nombre": "Dos Hermanas",
      "goles_local": 2,
      "goles_visitante": 1,
      "estado": "jugado"
    },
    {
      "fixture_id": "dzrzjoCr",
      "jornada": 20,
      "fecha": "2026-01-31",
      "local": 1,
      "local_nombre": "AD Ceuta B",
      "visitante": 14,
      "visitante_nombre": "RB Linense",
      "goles_local": 2,
      "goles_visitante": 0,
      "estado": "jugado"
    },
    {
      "fixture_id": "jyG28gS9",
      "jornada": 20,
      "fecha": "2026-01-31",
      "local": 11,
      "local_nombre": "Córdoba B",
      "visitante": 16,
      "visitante_nombre": "Sevilla C",
      "goles_local": 0,
      "goles_visitante": 0,
      "estado": "jugado"
    },
    {
      "fixture_id": "4rz8nC5j",
      "jornada": 20,
      "fecha": "2026-02-01",
      "local": 8,
      "local_nombre": "Conil",
      "visitante": 7,
      "visitante_nombre": "Ciudad de Lucena",
      "goles_local": 3,
      "goles_visitante": 2,
      "estado": "jugado"
    },
    {
      "fixture_id": "4bvW963E",
      "jornada": 20,
      "fecha": "2026-02-01",
      "local": 15,
      "local_nombre": "San Roque de Lepe",
      "visitante": 17,
      "visitante_nombre": "Tomares",
      "goles_local": 1,
      "goles_visitante": 0,
      "estado": "jugado"
    },
    {
      "fixture_id": "QFZjn3B7",
      "jornada": 20,
      "fecha": "2026-02-01",
      "local": 5,
      "local_nombre": "Castilleja",
      "visitante": 13,
      "visitante_nombre": "Pozoblanco",
      "goles_local": 0,
      "goles_visitante": 2,
      "estado": "jugado"
    },
    {
      "fixture_id": "pbgyhYsT",
      "jornada": 20,
      "fecha": "2026-02-01",
      "local": 3,
      "local_nombre": "Atletico Central",
      "visitante": 10,
      "visitante_nombre": "Cádiz B",
      "goles_local": 2,
      "goles_visitante": 0,
      "estado": "jugado"
    },
    {
      "fixture_id": "h2yqlPte",
      "jornada": 20,
      "fecha": "2026-02-01",
      "local": 9,
      "local_nombre": "Coria C.F.",
      "visitante": 2,
      "visitante_nombre": "Atl. Onubense",
      "goles_local": 2,
      "goles_visitante": 1,
      "estado": "jugado"
    },
    {
      "fixture_id": "CpeTgfDG",
      "jornada": 20,
      "fecha": "2026-02-01",
      "local": 18,
      "local_nombre": "Utrera",
      "visitante": 12,
      "visitante_nombre": "Dos Hermanas",
      "goles_local": 1,
      "goles_visitante": 3,
      "estado": "jugado"
    },
    {
      "fixture_id": "ULRgAFcc",
      "jornada": 20,
      "fecha": "2026-03-04",
      "local": 6,
      "local_nombre": "Chiclana",
      "visitante": 4,
      "visitante_nombre": "Bollullos",
      "goles_local": 2,
      "goles_visitante": 2,
      "estado": "jugado"
    },
    {
      "fixture_id": "4MMI02Q0",
      "jornada": 21,
      "fecha": "2026-02-11",
      "local": 10,
      "local_nombre": "Cádiz B",
      "visitante": 8,
      "visitante_nombre": "Conil",
      "goles_local": 0,
      "goles_visitante": 1,
      "estado": "jugado"
    },
    {
      "fixture_id": "pWUQbteD",
      "jornada": 21,
      "fecha": "2026-02-25",
      "local": 7,
      "local_nombre": "Ciudad de Lucena",
      "visitante": 6,
      "visitante_nombre": "Chiclana",
      "goles_local": 3,
      "goles_visitante": 0,
      "estado": "jugado"
    },
    {
      "fixture_id": "ddJA2Oel",
      "jornada": 21,
      "fecha": "2026-02-25",
      "local": 12,
      "local_nombre": "Dos Hermanas",
      "visitante": 3,
      "visitante_nombre": "Atletico Central",
      "goles_local": 3,
      "goles_visitante": 0,
      "estado": "jugado"
    },
    {
      "fixture_id": "4z2iF1uf",
      "jornada": 21,
      "fecha": "2026-03-11",
      "local": 14,
      "local_nombre": "RB Linense",
      "visitante": 9,
      "visitante_nombre": "Coria C.F.",
      "goles_local": 0,
      "goles_visitante": 0,
      "estado": "jugado"
    },
    {
      "fixture_id": "dAbqHNAs",
      "jornada": 21,
      "fecha": "2026-03-11",
      "local": 16,
      "local_nombre": "Sevilla C",
      "visitante": 1,
      "visitante_nombre": "AD Ceuta B",
      "goles_local": 3,
      "goles_visitante": 1,
      "estado": "jugado"
    },
    {
      "fixture_id": "manual_poz_srlepe_j21",
      "jornada": 21,
      "fecha": "2026-03-11",
      "local": 13,
      "local_nombre": "Pozoblanco",
      "visitante": 15,
      "visitante_nombre": "San Roque de Lepe",
      "goles_local": 4,
      "goles_visitante": 2,
      "estado": "jugado"
    },
    {
      "fixture_id": "Qkj0DuA6",
      "jornada": 21,
      "fecha": "2026-03-25",
      "local": 2,
      "local_nombre": "Atl. Onubense",
      "visitante": 5,
      "visitante_nombre": "Castilleja",
      "goles_local": null,
      "goles_visitante": null,
      "estado": "pendiente"
    },
    {
      "fixture_id": "xQHCMqmK",
      "jornada": 21,
      "fecha": "2026-04-01",
      "local": 4,
      "local_nombre": "Bollullos",
      "visitante": 11,
      "visitante_nombre": "Córdoba B",
      "goles_local": null,
      "goles_visitante": null,
      "estado": "pendiente"
    },
    {
      "fixture_id": "COsv8pYQ",
      "jornada": 21,
      "fecha": "2026-04-01",
      "local": 17,
      "local_nombre": "Tomares",
      "visitante": 18,
      "visitante_nombre": "Utrera",
      "goles_local": null,
      "goles_visitante": null,
      "estado": "pendiente"
    },
    {
      "fixture_id": "KCBZRvPa",
      "jornada": 22,
      "fecha": "2026-02-14",
      "local": 6,
      "local_nombre": "Chiclana",
      "visitante": 10,
      "visitante_nombre": "Cádiz B",
      "goles_local": 1,
      "goles_visitante": 1,
      "estado": "jugado"
    },
    {
      "fixture_id": "Ct5HxdwI",
      "jornada": 22,
      "fecha": "2026-02-15",
      "local": 13,
      "local_nombre": "Pozoblanco",
      "visitante": 17,
      "visitante_nombre": "Tomares",
      "goles_local": 1,
      "goles_visitante": 2,
      "estado": "jugado"
    },
    {
      "fixture_id": "6TZGvI85",
      "jornada": 22,
      "fecha": "2026-02-15",
      "local": 15,
      "local_nombre": "San Roque de Lepe",
      "visitante": 2,
      "visitante_nombre": "Atl. Onubense",
      "goles_local": 4,
      "goles_visitante": 0,
      "estado": "jugado"
    },
    {
      "fixture_id": "SEWfZMWP",
      "jornada": 22,
      "fecha": "2026-02-15",
      "local": 3,
      "local_nombre": "Atletico Central",
      "visitante": 18,
      "visitante_nombre": "Utrera",
      "goles_local": 0,
      "goles_visitante": 0,
      "estado": "jugado"
    },
    {
      "fixture_id": "Q9EsQIgC",
      "jornada": 22,
      "fecha": "2026-02-15",
      "local": 11,
      "local_nombre": "Córdoba B",
      "visitante": 7,
      "visitante_nombre": "Ciudad de Lucena",
      "goles_local": 0,
      "goles_visitante": 4,
      "estado": "jugado"
    },
    {
      "fixture_id": "nP2jOdOO",
      "jornada": 22,
      "fecha": "2026-02-15",
      "local": 1,
      "local_nombre": "AD Ceuta B",
      "visitante": 4,
      "visitante_nombre": "Bollullos",
      "goles_local": 1,
      "goles_visitante": 1,
      "estado": "jugado"
    },
    {
      "fixture_id": "YFy9tvvg",
      "jornada": 22,
      "fecha": "2026-02-15",
      "local": 5,
      "local_nombre": "Castilleja",
      "visitante": 14,
      "visitante_nombre": "RB Linense",
      "goles_local": 1,
      "goles_visitante": 1,
      "estado": "jugado"
    },
    {
      "fixture_id": "OpIQT0fm",
      "jornada": 22,
      "fecha": "2026-02-15",
      "local": 8,
      "local_nombre": "Conil",
      "visitante": 12,
      "visitante_nombre": "Dos Hermanas",
      "goles_local": 1,
      "goles_visitante": 3,
      "estado": "jugado"
    },
    {
      "fixture_id": "xlr0r09t",
      "jornada": 22,
      "fecha": "2026-02-15",
      "local": 9,
      "local_nombre": "Coria C.F.",
      "visitante": 16,
      "visitante_nombre": "Sevilla C",
      "goles_local": 1,
      "goles_visitante": 1,
      "estado": "jugado"
    },
    {
      "fixture_id": "dWiOYnxp",
      "jornada": 23,
      "fecha": "2026-02-21",
      "local": 7,
      "local_nombre": "Ciudad de Lucena",
      "visitante": 1,
      "visitante_nombre": "AD Ceuta B",
      "goles_local": 2,
      "goles_visitante": 0,
      "estado": "jugado"
    },
    {
      "fixture_id": "006hv9EM",
      "jornada": 23,
      "fecha": "2026-02-21",
      "local": 10,
      "local_nombre": "Cádiz B",
      "visitante": 11,
      "visitante_nombre": "Córdoba B",
      "goles_local": 3,
      "goles_visitante": 2,
      "estado": "jugado"
    },
    {
      "fixture_id": "SzQZjnbS",
      "jornada": 23,
      "fecha": "2026-02-22",
      "local": 2,
      "local_nombre": "Atl. Onubense",
      "visitante": 13,
      "visitante_nombre": "Pozoblanco",
      "goles_local": 0,
      "goles_visitante": 1,
      "estado": "jugado"
    },
    {
      "fixture_id": "tKRRh8TF",
      "jornada": 23,
      "fecha": "2026-02-22",
      "local": 14,
      "local_nombre": "RB Linense",
      "visitante": 15,
      "visitante_nombre": "San Roque de Lepe",
      "goles_local": 1,
      "goles_visitante": 1,
      "estado": "jugado"
    },
    {
      "fixture_id": "hboXWQ6d",
      "jornada": 23,
      "fecha": "2026-02-22",
      "local": 4,
      "local_nombre": "Bollullos",
      "visitante": 9,
      "visitante_nombre": "Coria C.F.",
      "goles_local": 1,
      "goles_visitante": 1,
      "estado": "jugado"
    },
    {
      "fixture_id": "61DqtVqA",
      "jornada": 23,
      "fecha": "2026-02-22",
      "local": 12,
      "local_nombre": "Dos Hermanas",
      "visitante": 6,
      "visitante_nombre": "Chiclana",
      "goles_local": 1,
      "goles_visitante": 1,
      "estado": "jugado"
    },
    {
      "fixture_id": "K4wJfUb3",
      "jornada": 23,
      "fecha": "2026-02-22",
      "local": 16,
      "local_nombre": "Sevilla C",
      "visitante": 5,
      "visitante_nombre": "Castilleja",
      "goles_local": 2,
      "goles_visitante": 0,
      "estado": "jugado"
    },
    {
      "fixture_id": "IuXlKmNj",
      "jornada": 23,
      "fecha": "2026-02-22",
      "local": 17,
      "local_nombre": "Tomares",
      "visitante": 3,
      "visitante_nombre": "Atletico Central",
      "goles_local": 1,
      "goles_visitante": 1,
      "estado": "jugado"
    },
    {
      "fixture_id": "byAyriFc",
      "jornada": 23,
      "fecha": "2026-02-22",
      "local": 18,
      "local_nombre": "Utrera",
      "visitante": 8,
      "visitante_nombre": "Conil",
      "goles_local": 0,
      "goles_visitante": 1,
      "estado": "jugado"
    },
    {
      "fixture_id": "Sl585oDL",
      "jornada": 24,
      "fecha": "2026-02-28",
      "local": 1,
      "local_nombre": "AD Ceuta B",
      "visitante": 10,
      "visitante_nombre": "Cádiz B",
      "goles_local": 1,
      "goles_visitante": 0,
      "estado": "jugado"
    },
    {
      "fixture_id": "Knpmb35e",
      "jornada": 24,
      "fecha": "2026-02-28",
      "local": 5,
      "local_nombre": "Castilleja",
      "visitante": 4,
      "visitante_nombre": "Bollullos",
      "goles_local": 0,
      "goles_visitante": 1,
      "estado": "jugado"
    },
    {
      "fixture_id": "nL66oQLk",
      "jornada": 24,
      "fecha": "2026-03-01",
      "local": 8,
      "local_nombre": "Conil",
      "visitante": 3,
      "visitante_nombre": "Atletico Central",
      "goles_local": 0,
      "goles_visitante": 0,
      "estado": "jugado"
    },
    {
      "fixture_id": "SAtqIOdR",
      "jornada": 24,
      "fecha": "2026-03-01",
      "local": 2,
      "local_nombre": "Atl. Onubense",
      "visitante": 17,
      "visitante_nombre": "Tomares",
      "goles_local": 0,
      "goles_visitante": 0,
      "estado": "jugado"
    },
    {
      "fixture_id": "KY4Eq4j2",
      "jornada": 24,
      "fecha": "2026-03-01",
      "local": 6,
      "local_nombre": "Chiclana",
      "visitante": 18,
      "visitante_nombre": "Utrera",
      "goles_local": 0,
      "goles_visitante": 2,
      "estado": "jugado"
    },
    {
      "fixture_id": "zsm177r9",
      "jornada": 24,
      "fecha": "2026-03-01",
      "local": 11,
      "local_nombre": "Córdoba B",
      "visitante": 12,
      "visitante_nombre": "Dos Hermanas",
      "goles_local": 2,
      "goles_visitante": 2,
      "estado": "jugado"
    },
    {
      "fixture_id": "CMtu0Pzq",
      "jornada": 24,
      "fecha": "2026-03-01",
      "local": 9,
      "local_nombre": "Coria C.F.",
      "visitante": 7,
      "visitante_nombre": "Ciudad de Lucena",
      "goles_local": 0,
      "goles_visitante": 1,
      "estado": "jugado"
    },
    {
      "fixture_id": "88QsKpSE",
      "jornada": 24,
      "fecha": "2026-03-01",
      "local": 13,
      "local_nombre": "Pozoblanco",
      "visitante": 14,
      "visitante_nombre": "RB Linense",
      "goles_local": 0,
      "goles_visitante": 0,
      "estado": "jugado"
    },
    {
      "fixture_id": "GEwddsz8",
      "jornada": 24,
      "fecha": "2026-03-01",
      "local": 15,
      "local_nombre": "San Roque de Lepe",
      "visitante": 16,
      "visitante_nombre": "Sevilla C",
      "goles_local": 2,
      "goles_visitante": 1,
      "estado": "jugado"
    },
    {
      "fixture_id": "tGHu0pht",
      "jornada": 25,
      "fecha": "2026-03-07",
      "local": 12,
      "local_nombre": "Dos Hermanas",
      "visitante": 1,
      "visitante_nombre": "AD Ceuta B",
      "goles_local": 3,
      "goles_visitante": 0,
      "estado": "jugado"
    },
    {
      "fixture_id": "Ae9dd2i5",
      "jornada": 25,
      "fecha": "2026-03-08",
      "local": 7,
      "local_nombre": "Ciudad de Lucena",
      "visitante": 5,
      "visitante_nombre": "Castilleja",
      "goles_local": 5,
      "goles_visitante": 0,
      "estado": "jugado"
    },
    {
      "fixture_id": "ILC4ftMH",
      "jornada": 25,
      "fecha": "2026-03-08",
      "local": 4,
      "local_nombre": "Bollullos",
      "visitante": 15,
      "visitante_nombre": "San Roque de Lepe",
      "goles_local": 2,
      "goles_visitante": 2,
      "estado": "jugado"
    },
    {
      "fixture_id": "vy1DhKjU",
      "jornada": 25,
      "fecha": "2026-03-08",
      "local": 16,
      "local_nombre": "Sevilla C",
      "visitante": 13,
      "visitante_nombre": "Pozoblanco",
      "goles_local": 3,
      "goles_visitante": 0,
      "estado": "jugado"
    },
    {
      "fixture_id": "K8LNAtk1",
      "jornada": 25,
      "fecha": "2026-03-08",
      "local": 3,
      "local_nombre": "Atletico Central",
      "visitante": 6,
      "visitante_nombre": "Chiclana",
      "goles_local": 0,
      "goles_visitante": 0,
      "estado": "jugado"
    },
    {
      "fixture_id": "ETFmbOMh",
      "jornada": 25,
      "fecha": "2026-03-08",
      "local": 10,
      "local_nombre": "Cádiz B",
      "visitante": 9,
      "visitante_nombre": "Coria C.F.",
      "goles_local": 1,
      "goles_visitante": 0,
      "estado": "jugado"
    },
    {
      "fixture_id": "f1jMCNyn",
      "jornada": 25,
      "fecha": "2026-03-08",
      "local": 14,
      "local_nombre": "RB Linense",
      "visitante": 2,
      "visitante_nombre": "Atl. Onubense",
      "goles_local": 1,
      "goles_visitante": 2,
      "estado": "jugado"
    },
    {
      "fixture_id": "bgXEC2Kl",
      "jornada": 25,
      "fecha": "2026-03-08",
      "local": 17,
      "local_nombre": "Tomares",
      "visitante": 8,
      "visitante_nombre": "Conil",
      "goles_local": 1,
      "goles_visitante": 2,
      "estado": "jugado"
    },
    {
      "fixture_id": "SYOV8KJD",
      "jornada": 25,
      "fecha": "2026-03-08",
      "local": 18,
      "local_nombre": "Utrera",
      "visitante": 11,
      "visitante_nombre": "Córdoba B",
      "goles_local": 1,
      "goles_visitante": 1,
      "estado": "jugado"
    },
    {
      "fixture_id": "Otrw9uyB",
      "jornada": 26,
      "fecha": "2026-03-14",
      "local": 11,
      "local_nombre": "Córdoba B",
      "visitante": 3,
      "visitante_nombre": "Atletico Central",
      "goles_local": 1,
      "goles_visitante": 1,
      "estado": "jugado"
    },
    {
      "fixture_id": "K8yn7J5N",
      "jornada": 26,
      "fecha": "2026-03-14",
      "local": 1,
      "local_nombre": "AD Ceuta B",
      "visitante": 18,
      "visitante_nombre": "Utrera",
      "goles_local": 1,
      "goles_visitante": 1,
      "estado": "jugado"
    },
    {
      "fixture_id": "UJ44P0Li",
      "jornada": 26,
      "fecha": "2026-03-15",
      "local": 5,
      "local_nombre": "Castilleja",
      "visitante": 10,
      "visitante_nombre": "Cádiz B",
      "goles_local": null,
      "goles_visitante": null,
      "estado": "pendiente"
    },
    {
      "fixture_id": "6PaTJdkT",
      "jornada": 26,
      "fecha": "2026-03-15",
      "local": 2,
      "local_nombre": "Atl. Onubense",
      "visitante": 16,
      "visitante_nombre": "Sevilla C",
      "goles_local": null,
      "goles_visitante": null,
      "estado": "pendiente"
    },
    {
      "fixture_id": "jTqVA16b",
      "jornada": 26,
      "fecha": "2026-03-15",
      "local": 6,
      "local_nombre": "Chiclana",
      "visitante": 8,
      "visitante_nombre": "Conil",
      "goles_local": null,
      "goles_visitante": null,
      "estado": "pendiente"
    },
    {
      "fixture_id": "lORH1cTp",
      "jornada": 26,
      "fecha": "2026-03-15",
      "local": 9,
      "local_nombre": "Coria C.F.",
      "visitante": 12,
      "visitante_nombre": "Dos Hermanas",
      "goles_local": null,
      "goles_visitante": null,
      "estado": "pendiente"
    },
    {
      "fixture_id": "YB1LLIKG",
      "jornada": 26,
      "fecha": "2026-03-15",
      "local": 13,
      "local_nombre": "Pozoblanco",
      "visitante": 4,
      "visitante_nombre": "Bollullos",
      "goles_local": null,
      "goles_visitante": null,
      "estado": "pendiente"
    },
    {
      "fixture_id": "lp3hEzDj",
      "jornada": 26,
      "fecha": "2026-03-15",
      "local": 14,
      "local_nombre": "RB Linense",
      "visitante": 17,
      "visitante_nombre": "Tomares",
      "goles_local": null,
      "goles_visitante": null,
      "estado": "pendiente"
    },
    {
      "fixture_id": "xp8CNvj4",
      "jornada": 26,
      "fecha": "2026-03-15",
      "local": 15,
      "local_nombre": "San Roque de Lepe",
      "visitante": 7,
      "visitante_nombre": "Ciudad de Lucena",
      "goles_local": null,
      "goles_visitante": null,
      "estado": "pendiente"
    },
    {
      "fixture_id": "lbrRSZRq",
      "jornada": 27,
      "fecha": "2026-03-22",
      "local": 18,
      "local_nombre": "Utrera",
      "visitante": 9,
      "visitante_nombre": "Coria C.F.",
      "goles_local": null,
      "goles_visitante": null,
      "estado": "pendiente"
    },
    {
      "fixture_id": "pWneYe4M",
      "jornada": 27,
      "fecha": "2026-03-22",
      "local": 3,
      "local_nombre": "Atletico Central",
      "visitante": 1,
      "visitante_nombre": "AD Ceuta B",
      "goles_local": null,
      "goles_visitante": null,
      "estado": "pendiente"
    },
    {
      "fixture_id": "4Yv2Un3l",
      "jornada": 27,
      "fecha": "2026-03-22",
      "local": 4,
      "local_nombre": "Bollullos",
      "visitante": 2,
      "visitante_nombre": "Atl. Onubense",
      "goles_local": null,
      "goles_visitante": null,
      "estado": "pendiente"
    },
    {
      "fixture_id": "xKOLlHl3",
      "jornada": 27,
      "fecha": "2026-03-22",
      "local": 10,
      "local_nombre": "Cádiz B",
      "visitante": 15,
      "visitante_nombre": "San Roque de Lepe",
      "goles_local": null,
      "goles_visitante": null,
      "estado": "pendiente"
    },
    {
      "fixture_id": "ppSTneJF",
      "jornada": 27,
      "fecha": "2026-03-22",
      "local": 7,
      "local_nombre": "Ciudad de Lucena",
      "visitante": 13,
      "visitante_nombre": "Pozoblanco",
      "goles_local": null,
      "goles_visitante": null,
      "estado": "pendiente"
    },
    {
      "fixture_id": "x6qmzIZ9",
      "jornada": 27,
      "fecha": "2026-03-22",
      "local": 8,
      "local_nombre": "Conil",
      "visitante": 11,
      "visitante_nombre": "Córdoba B",
      "goles_local": null,
      "goles_visitante": null,
      "estado": "pendiente"
    },
    {
      "fixture_id": "MBtZQDdd",
      "jornada": 27,
      "fecha": "2026-03-22",
      "local": 12,
      "local_nombre": "Dos Hermanas",
      "visitante": 5,
      "visitante_nombre": "Castilleja",
      "goles_local": null,
      "goles_visitante": null,
      "estado": "pendiente"
    },
    {
      "fixture_id": "jkwASQX0",
      "jornada": 27,
      "fecha": "2026-03-22",
      "local": 16,
      "local_nombre": "Sevilla C",
      "visitante": 14,
      "visitante_nombre": "RB Linense",
      "goles_local": null,
      "goles_visitante": null,
      "estado": "pendiente"
    },
    {
      "fixture_id": "Gjevxv5c",
      "jornada": 27,
      "fecha": "2026-03-22",
      "local": 17,
      "local_nombre": "Tomares",
      "visitante": 6,
      "visitante_nombre": "Chiclana",
      "goles_local": null,
      "goles_visitante": null,
      "estado": "pendiente"
    },
    {
      "fixture_id": "vBJ4l8fK",
      "jornada": 28,
      "fecha": "2026-03-29",
      "local": 1,
      "local_nombre": "AD Ceuta B",
      "visitante": 8,
      "visitante_nombre": "Conil",
      "goles_local": null,
      "goles_visitante": null,
      "estado": "pendiente"
    },
    {
      "fixture_id": "ltwm1ovQ",
      "jornada": 28,
      "fecha": "2026-03-29",
      "local": 2,
      "local_nombre": "Atl. Onubense",
      "visitante": 7,
      "visitante_nombre": "Ciudad de Lucena",
      "goles_local": null,
      "goles_visitante": null,
      "estado": "pendiente"
    },
    {
      "fixture_id": "4h3qsQnf",
      "jornada": 28,
      "fecha": "2026-03-29",
      "local": 5,
      "local_nombre": "Castilleja",
      "visitante": 18,
      "visitante_nombre": "Utrera",
      "goles_local": null,
      "goles_visitante": null,
      "estado": "pendiente"
    },
    {
      "fixture_id": "nHWIQ42D",
      "jornada": 28,
      "fecha": "2026-03-29",
      "local": 11,
      "local_nombre": "Córdoba B",
      "visitante": 6,
      "visitante_nombre": "Chiclana",
      "goles_local": null,
      "goles_visitante": null,
      "estado": "pendiente"
    },
    {
      "fixture_id": "be0yqnIs",
      "jornada": 28,
      "fecha": "2026-03-29",
      "local": 9,
      "local_nombre": "Coria C.F.",
      "visitante": 3,
      "visitante_nombre": "Atletico Central",
      "goles_local": null,
      "goles_visitante": null,
      "estado": "pendiente"
    },
    {
      "fixture_id": "YXf0wrnJ",
      "jornada": 28,
      "fecha": "2026-03-29",
      "local": 13,
      "local_nombre": "Pozoblanco",
      "visitante": 10,
      "visitante_nombre": "Cádiz B",
      "goles_local": null,
      "goles_visitante": null,
      "estado": "pendiente"
    },
    {
      "fixture_id": "pCOIeP1m",
      "jornada": 28,
      "fecha": "2026-03-29",
      "local": 14,
      "local_nombre": "RB Linense",
      "visitante": 4,
      "visitante_nombre": "Bollullos",
      "goles_local": null,
      "goles_visitante": null,
      "estado": "pendiente"
    },
    {
      "fixture_id": "Q7ihu4H6",
      "jornada": 28,
      "fecha": "2026-03-29",
      "local": 15,
      "local_nombre": "San Roque de Lepe",
      "visitante": 12,
      "visitante_nombre": "Dos Hermanas",
      "goles_local": null,
      "goles_visitante": null,
      "estado": "pendiente"
    },
    {
      "fixture_id": "jPgJg3Wa",
      "jornada": 28,
      "fecha": "2026-03-29",
      "local": 16,
      "local_nombre": "Sevilla C",
      "visitante": 17,
      "visitante_nombre": "Tomares",
      "goles_local": null,
      "goles_visitante": null,
      "estado": "pendiente"
    },
    {
      "fixture_id": "4SJh82og",
      "jornada": 29,
      "fecha": "2026-04-05",
      "local": 3,
      "local_nombre": "Atletico Central",
      "visitante": 5,
      "visitante_nombre": "Castilleja",
      "goles_local": null,
      "goles_visitante": null,
      "estado": "pendiente"
    },
    {
      "fixture_id": "W2wzLuVb",
      "jornada": 29,
      "fecha": "2026-04-05",
      "local": 4,
      "local_nombre": "Bollullos",
      "visitante": 16,
      "visitante_nombre": "Sevilla C",
      "goles_local": null,
      "goles_visitante": null,
      "estado": "pendiente"
    },
    {
      "fixture_id": "tYEH2bFU",
      "jornada": 29,
      "fecha": "2026-04-05",
      "local": 10,
      "local_nombre": "Cádiz B",
      "visitante": 2,
      "visitante_nombre": "Atl. Onubense",
      "goles_local": null,
      "goles_visitante": null,
      "estado": "pendiente"
    },
    {
      "fixture_id": "K4ozjLVO",
      "jornada": 29,
      "fecha": "2026-04-05",
      "local": 6,
      "local_nombre": "Chiclana",
      "visitante": 1,
      "visitante_nombre": "AD Ceuta B",
      "goles_local": null,
      "goles_visitante": null,
      "estado": "pendiente"
    },
    {
      "fixture_id": "pnuSM10n",
      "jornada": 29,
      "fecha": "2026-04-05",
      "local": 7,
      "local_nombre": "Ciudad de Lucena",
      "visitante": 14,
      "visitante_nombre": "RB Linense",
      "goles_local": null,
      "goles_visitante": null,
      "estado": "pendiente"
    },
    {
      "fixture_id": "ATQqAOGt",
      "jornada": 29,
      "fecha": "2026-04-05",
      "local": 8,
      "local_nombre": "Conil",
      "visitante": 9,
      "visitante_nombre": "Coria C.F.",
      "goles_local": null,
      "goles_visitante": null,
      "estado": "pendiente"
    },
    {
      "fixture_id": "Y7B94KpI",
      "jornada": 29,
      "fecha": "2026-04-05",
      "local": 12,
      "local_nombre": "Dos Hermanas",
      "visitante": 13,
      "visitante_nombre": "Pozoblanco",
      "goles_local": null,
      "goles_visitante": null,
      "estado": "pendiente"
    },
    {
      "fixture_id": "bkcRis1C",
      "jornada": 29,
      "fecha": "2026-04-05",
      "local": 17,
      "local_nombre": "Tomares",
      "visitante": 11,
      "visitante_nombre": "Córdoba B",
      "goles_local": null,
      "goles_visitante": null,
      "estado": "pendiente"
    },
    {
      "fixture_id": "xtI06tG5",
      "jornada": 29,
      "fecha": "2026-04-05",
      "local": 18,
      "local_nombre": "Utrera",
      "visitante": 15,
      "visitante_nombre": "San Roque de Lepe",
      "goles_local": null,
      "goles_visitante": null,
      "estado": "pendiente"
    },
    {
      "fixture_id": "SUWrJJaB",
      "jornada": 30,
      "fecha": "2026-04-12",
      "local": 1,
      "local_nombre": "AD Ceuta B",
      "visitante": 11,
      "visitante_nombre": "Córdoba B",
      "goles_local": null,
      "goles_visitante": null,
      "estado": "pendiente"
    },
    {
      "fixture_id": "zDoRIA5S",
      "jornada": 30,
      "fecha": "2026-04-12",
      "local": 2,
      "local_nombre": "Atl. Onubense",
      "visitante": 12,
      "visitante_nombre": "Dos Hermanas",
      "goles_local": null,
      "goles_visitante": null,
      "estado": "pendiente"
    },
    {
      "fixture_id": "8MHrJvH8",
      "jornada": 30,
      "fecha": "2026-04-12",
      "local": 4,
      "local_nombre": "Bollullos",
      "visitante": 17,
      "visitante_nombre": "Tomares",
      "goles_local": null,
      "goles_visitante": null,
      "estado": "pendiente"
    },
    {
      "fixture_id": "fqmPbkEd",
      "jornada": 30,
      "fecha": "2026-04-12",
      "local": 5,
      "local_nombre": "Castilleja",
      "visitante": 8,
      "visitante_nombre": "Conil",
      "goles_local": null,
      "goles_visitante": null,
      "estado": "pendiente"
    },
    {
      "fixture_id": "bHgG0Bqp",
      "jornada": 30,
      "fecha": "2026-04-12",
      "local": 9,
      "local_nombre": "Coria C.F.",
      "visitante": 6,
      "visitante_nombre": "Chiclana",
      "goles_local": null,
      "goles_visitante": null,
      "estado": "pendiente"
    },
    {
      "fixture_id": "SnrJKWzG",
      "jornada": 30,
      "fecha": "2026-04-12",
      "local": 13,
      "local_nombre": "Pozoblanco",
      "visitante": 18,
      "visitante_nombre": "Utrera",
      "goles_local": null,
      "goles_visitante": null,
      "estado": "pendiente"
    },
    {
      "fixture_id": "fcScDlTk",
      "jornada": 30,
      "fecha": "2026-04-12",
      "local": 14,
      "local_nombre": "RB Linense",
      "visitante": 10,
      "visitante_nombre": "Cádiz B",
      "goles_local": null,
      "goles_visitante": null,
      "estado": "pendiente"
    },
    {
      "fixture_id": "6XgAMh63",
      "jornada": 30,
      "fecha": "2026-04-12",
      "local": 15,
      "local_nombre": "San Roque de Lepe",
      "visitante": 3,
      "visitante_nombre": "Atletico Central",
      "goles_local": null,
      "goles_visitante": null,
      "estado": "pendiente"
    },
    {
      "fixture_id": "SAQ5BSc2",
      "jornada": 30,
      "fecha": "2026-04-12",
      "local": 16,
      "local_nombre": "Sevilla C",
      "visitante": 7,
      "visitante_nombre": "Ciudad de Lucena",
      "goles_local": null,
      "goles_visitante": null,
      "estado": "pendiente"
    },
    {
      "fixture_id": "fwtQVH0E",
      "jornada": 31,
      "fecha": "2026-04-19",
      "local": 3,
      "local_nombre": "Atletico Central",
      "visitante": 13,
      "visitante_nombre": "Pozoblanco",
      "goles_local": null,
      "goles_visitante": null,
      "estado": "pendiente"
    },
    {
      "fixture_id": "r3EDMDN0",
      "jornada": 31,
      "fecha": "2026-04-19",
      "local": 10,
      "local_nombre": "Cádiz B",
      "visitante": 16,
      "visitante_nombre": "Sevilla C",
      "goles_local": null,
      "goles_visitante": null,
      "estado": "pendiente"
    },
    {
      "fixture_id": "8p0V9zve",
      "jornada": 31,
      "fecha": "2026-04-19",
      "local": 6,
      "local_nombre": "Chiclana",
      "visitante": 5,
      "visitante_nombre": "Castilleja",
      "goles_local": null,
      "goles_visitante": null,
      "estado": "pendiente"
    },
    {
      "fixture_id": "GURKKihD",
      "jornada": 31,
      "fecha": "2026-04-19",
      "local": 7,
      "local_nombre": "Ciudad de Lucena",
      "visitante": 4,
      "visitante_nombre": "Bollullos",
      "goles_local": null,
      "goles_visitante": null,
      "estado": "pendiente"
    },
    {
      "fixture_id": "2qgv8E87",
      "jornada": 31,
      "fecha": "2026-04-19",
      "local": 8,
      "local_nombre": "Conil",
      "visitante": 15,
      "visitante_nombre": "San Roque de Lepe",
      "goles_local": null,
      "goles_visitante": null,
      "estado": "pendiente"
    },
    {
      "fixture_id": "0KdNBd9r",
      "jornada": 31,
      "fecha": "2026-04-19",
      "local": 11,
      "local_nombre": "Córdoba B",
      "visitante": 9,
      "visitante_nombre": "Coria C.F.",
      "goles_local": null,
      "goles_visitante": null,
      "estado": "pendiente"
    },
    {
      "fixture_id": "MmQ4OZhl",
      "jornada": 31,
      "fecha": "2026-04-19",
      "local": 12,
      "local_nombre": "Dos Hermanas",
      "visitante": 14,
      "visitante_nombre": "RB Linense",
      "goles_local": null,
      "goles_visitante": null,
      "estado": "pendiente"
    },
    {
      "fixture_id": "GnLjHIoL",
      "jornada": 31,
      "fecha": "2026-04-19",
      "local": 17,
      "local_nombre": "Tomares",
      "visitante": 1,
      "visitante_nombre": "AD Ceuta B",
      "goles_local": null,
      "goles_visitante": null,
      "estado": "pendiente"
    },
    {
      "fixture_id": "j5ZYTeVQ",
      "jornada": 31,
      "fecha": "2026-04-19",
      "local": 18,
      "local_nombre": "Utrera",
      "visitante": 2,
      "visitante_nombre": "Atl. Onubense",
      "goles_local": null,
      "goles_visitante": null,
      "estado": "pendiente"
    },
    {
      "fixture_id": "jmt3XUyJ",
      "jornada": 32,
      "fecha": "2026-04-26",
      "local": 2,
      "local_nombre": "Atl. Onubense",
      "visitante": 3,
      "visitante_nombre": "Atletico Central",
      "goles_local": null,
      "goles_visitante": null,
      "estado": "pendiente"
    },
    {
      "fixture_id": "p8lVz4rB",
      "jornada": 32,
      "fecha": "2026-04-26",
      "local": 4,
      "local_nombre": "Bollullos",
      "visitante": 10,
      "visitante_nombre": "Cádiz B",
      "goles_local": null,
      "goles_visitante": null,
      "estado": "pendiente"
    },
    {
      "fixture_id": "S8ewwZ7s",
      "jornada": 32,
      "fecha": "2026-04-26",
      "local": 5,
      "local_nombre": "Castilleja",
      "visitante": 11,
      "visitante_nombre": "Córdoba B",
      "goles_local": null,
      "goles_visitante": null,
      "estado": "pendiente"
    },
    {
      "fixture_id": "4A4WYsDN",
      "jornada": 32,
      "fecha": "2026-04-26",
      "local": 7,
      "local_nombre": "Ciudad de Lucena",
      "visitante": 17,
      "visitante_nombre": "Tomares",
      "goles_local": null,
      "goles_visitante": null,
      "estado": "pendiente"
    },
    {
      "fixture_id": "WxA7repK",
      "jornada": 32,
      "fecha": "2026-04-26",
      "local": 9,
      "local_nombre": "Coria C.F.",
      "visitante": 1,
      "visitante_nombre": "AD Ceuta B",
      "goles_local": null,
      "goles_visitante": null,
      "estado": "pendiente"
    },
    {
      "fixture_id": "UXifZj76",
      "jornada": 32,
      "fecha": "2026-04-26",
      "local": 13,
      "local_nombre": "Pozoblanco",
      "visitante": 8,
      "visitante_nombre": "Conil",
      "goles_local": null,
      "goles_visitante": null,
      "estado": "pendiente"
    },
    {
      "fixture_id": "GSdEvnqn",
      "jornada": 32,
      "fecha": "2026-04-26",
      "local": 14,
      "local_nombre": "RB Linense",
      "visitante": 18,
      "visitante_nombre": "Utrera",
      "goles_local": null,
      "goles_visitante": null,
      "estado": "pendiente"
    },
    {
      "fixture_id": "OzknyDxf",
      "jornada": 32,
      "fecha": "2026-04-26",
      "local": 15,
      "local_nombre": "San Roque de Lepe",
      "visitante": 6,
      "visitante_nombre": "Chiclana",
      "goles_local": null,
      "goles_visitante": null,
      "estado": "pendiente"
    },
    {
      "fixture_id": "CfjNxQDb",
      "jornada": 32,
      "fecha": "2026-04-26",
      "local": 16,
      "local_nombre": "Sevilla C",
      "visitante": 12,
      "visitante_nombre": "Dos Hermanas",
      "goles_local": null,
      "goles_visitante": null,
      "estado": "pendiente"
    },
    {
      "fixture_id": "GlYliPSi",
      "jornada": 33,
      "fecha": "2026-05-03",
      "local": 1,
      "local_nombre": "AD Ceuta B",
      "visitante": 5,
      "visitante_nombre": "Castilleja",
      "goles_local": null,
      "goles_visitante": null,
      "estado": "pendiente"
    },
    {
      "fixture_id": "dMOqtaKj",
      "jornada": 33,
      "fecha": "2026-05-03",
      "local": 3,
      "local_nombre": "Atletico Central",
      "visitante": 14,
      "visitante_nombre": "RB Linense",
      "goles_local": null,
      "goles_visitante": null,
      "estado": "pendiente"
    },
    {
      "fixture_id": "Wb3n0KBM",
      "jornada": 33,
      "fecha": "2026-05-03",
      "local": 10,
      "local_nombre": "Cádiz B",
      "visitante": 7,
      "visitante_nombre": "Ciudad de Lucena",
      "goles_local": null,
      "goles_visitante": null,
      "estado": "pendiente"
    },
    {
      "fixture_id": "4Oq5msSG",
      "jornada": 33,
      "fecha": "2026-05-03",
      "local": 6,
      "local_nombre": "Chiclana",
      "visitante": 13,
      "visitante_nombre": "Pozoblanco",
      "goles_local": null,
      "goles_visitante": null,
      "estado": "pendiente"
    },
    {
      "fixture_id": "xxrDoLdT",
      "jornada": 33,
      "fecha": "2026-05-03",
      "local": 8,
      "local_nombre": "Conil",
      "visitante": 2,
      "visitante_nombre": "Atl. Onubense",
      "goles_local": null,
      "goles_visitante": null,
      "estado": "pendiente"
    },
    {
      "fixture_id": "OEyck3c4",
      "jornada": 33,
      "fecha": "2026-05-03",
      "local": 11,
      "local_nombre": "Córdoba B",
      "visitante": 15,
      "visitante_nombre": "San Roque de Lepe",
      "goles_local": null,
      "goles_visitante": null,
      "estado": "pendiente"
    },
    {
      "fixture_id": "zge2TLzo",
      "jornada": 33,
      "fecha": "2026-05-03",
      "local": 9,
      "local_nombre": "Coria C.F.",
      "visitante": 17,
      "visitante_nombre": "Tomares",
      "goles_local": null,
      "goles_visitante": null,
      "estado": "pendiente"
    },
    {
      "fixture_id": "pr5v2tsA",
      "jornada": 33,
      "fecha": "2026-05-03",
      "local": 12,
      "local_nombre": "Dos Hermanas",
      "visitante": 4,
      "visitante_nombre": "Bollullos",
      "goles_local": null,
      "goles_visitante": null,
      "estado": "pendiente"
    },
    {
      "fixture_id": "OSGV32Cc",
      "jornada": 33,
      "fecha": "2026-05-03",
      "local": 18,
      "local_nombre": "Utrera",
      "visitante": 16,
      "visitante_nombre": "Sevilla C",
      "goles_local": null,
      "goles_visitante": null,
      "estado": "pendiente"
    },
    {
      "fixture_id": "p2TLEJQF",
      "jornada": 34,
      "fecha": "2026-05-10",
      "local": 2,
      "local_nombre": "Atl. Onubense",
      "visitante": 6,
      "visitante_nombre": "Chiclana",
      "goles_local": null,
      "goles_visitante": null,
      "estado": "pendiente"
    },
    {
      "fixture_id": "YR195Fm2",
      "jornada": 34,
      "fecha": "2026-05-10",
      "local": 4,
      "local_nombre": "Bollullos",
      "visitante": 18,
      "visitante_nombre": "Utrera",
      "goles_local": null,
      "goles_visitante": null,
      "estado": "pendiente"
    },
    {
      "fixture_id": "jqpJfbZq",
      "jornada": 34,
      "fecha": "2026-05-10",
      "local": 5,
      "local_nombre": "Castilleja",
      "visitante": 9,
      "visitante_nombre": "Coria C.F.",
      "goles_local": null,
      "goles_visitante": null,
      "estado": "pendiente"
    },
    {
      "fixture_id": "QLleTIu9",
      "jornada": 34,
      "fecha": "2026-05-10",
      "local": 7,
      "local_nombre": "Ciudad de Lucena",
      "visitante": 12,
      "visitante_nombre": "Dos Hermanas",
      "goles_local": null,
      "goles_visitante": null,
      "estado": "pendiente"
    },
    {
      "fixture_id": "v5QDGud3",
      "jornada": 34,
      "fecha": "2026-05-10",
      "local": 13,
      "local_nombre": "Pozoblanco",
      "visitante": 11,
      "visitante_nombre": "Córdoba B",
      "goles_local": null,
      "goles_visitante": null,
      "estado": "pendiente"
    },
    {
      "fixture_id": "6HHUCceS",
      "jornada": 34,
      "fecha": "2026-05-10",
      "local": 14,
      "local_nombre": "RB Linense",
      "visitante": 8,
      "visitante_nombre": "Conil",
      "goles_local": null,
      "goles_visitante": null,
      "estado": "pendiente"
    },
    {
      "fixture_id": "OdrRhx4d",
      "jornada": 34,
      "fecha": "2026-05-10",
      "local": 15,
      "local_nombre": "San Roque de Lepe",
      "visitante": 1,
      "visitante_nombre": "AD Ceuta B",
      "goles_local": null,
      "goles_visitante": null,
      "estado": "pendiente"
    },
    {
      "fixture_id": "x0807yJk",
      "jornada": 34,
      "fecha": "2026-05-10",
      "local": 16,
      "local_nombre": "Sevilla C",
      "visitante": 3,
      "visitante_nombre": "Atletico Central",
      "goles_local": null,
      "goles_visitante": null,
      "estado": "pendiente"
    },
    {
      "fixture_id": "U7rLAAPs",
      "jornada": 34,
      "fecha": "2026-05-10",
      "local": 17,
      "local_nombre": "Tomares",
      "visitante": 10,
      "visitante_nombre": "Cádiz B",
      "goles_local": null,
      "goles_visitante": null,
      "estado": "pendiente"
    }
  ]
}